{
  "description": "### КЛАССОВЫЕ УМЕНИЯ\n\nКак механик, вы обладаете следующими особенностями класса.\n\n#### ХИТЫ\n\n* **Кость хитов:** 1d10 за уровень механика.\n* **Хиты на 1-м уровне:** 10 + ваш модификатор ТЕЛ.\n* **Хиты на более высоких уровнях:** 1d10 (или 6) + ваш модификатор ТЕЛ за каждый уровень механика после 1-го.\n\n#### ВЛАДЕНИЯ\n\n* **Доспехи:** Лёгкие доспехи, средние доспехи и щиты.\n* **Оружие:** Простое оружие, воинское оружие.\n* **Инструменты:** Инструменты механика и два дополнительных инструмента на ваш выбор.\n* **Спасброски:** ТЕЛ, ИНТ.\n* **Навыки:** Выберите два из следующих: Магия, История, Расследование, Внимательность и Ловкость рук.\n\n#### НАЧАЛЬНОЕ СНАРЯЖЕНИЕ\n\nВы начинаете со следующим снаряжением, в дополнение к снаряжению, предоставленному вашей предысторией:\n\n* (a) воинское оружие и щит или (b) два простых оружия.\n* Лёгкий арбалет и 20 болтов.\n* (a) чешуйчатый доспех или (b) кожаный доспех.\n* Инструменты механика и набор исследователя подземелий.\n  \n#### ПРОГРЕССИЯ МЕХАНИСТА\n\n| УРОВЕНЬ | БМ | ЭФФЕКТЫ АУГМЕНТАЦИИ | УСИЛЕННЫЕ ПРЕДМЕТЫ | УМЕНИЯ |\n|---|---|---|---|---|\n| 1-й | +2 | — | — | Глаза Создателя, Осколок Творения |\n| 2-й | +2 | 2 | 3 | Аугментация, Эффективное Действие |\n| 3-й | +2 | 3 | 3 | Подкласс Механиста |\n| 4-й | +2 | 3 | 3 | Улучшение |\n| 5-й | +3 | 4 | 4 | Мультиатака (2/Действие Атаки) |\n| 6-й | +3 | 4 | 4 | Быстрая Аугментация |\n| 7-й | +3 | 5 | 4 | Особенность Подкласса |\n| 8-й | +3 | 5 | 4 | Улучшение |\n| 9-й | +4 | 6 | 5 | Великое Творение |\n| 10-й | +4 | 6 | 5 | Героический Дар |\n| 11-й | +4 | 6 | 5 | Особенность Подкласса |\n| 12-й | +4 | 7 | 5 | Улучшение |\n| 13-й | +5 | 7 | 6 | Проницательность Инженера |\n| 14-й | +5 | 7 | 6 | Дальняя Аугментация |\n| 15-й | +5 | 8 | 6 | Особенность Подкласса |\n| 16-й | +5 | 8 | 6 | Улучшение |\n| 17-й | +6 | 8 | 7 | Всегда Готов |\n| 18-й | +6 | 9 | 7 | Совершенное Творение |\n| 19-й | +6 | 9 | 7 | Улучшение |\n| 20-й | +6 | 9 | 7 | Эпический Дар |\n\n#### ГЛАЗА ТВОРЦА\n\n**Умение механика 1-го уровня**\n\nКогда вы касаетесь магического предмета или какого-либо другого объекта, наделённого магией, вы узнаёте его свойства и то, как его использовать, требуется ли для его использования настройка и сколько у него зарядов (если таковые имеются). Вы узнаёте, какие заклинания воздействуют на предмет и что это за заклинания. Если предмет был создан заклинанием, вы узнаёте, какое заклинание его создало.\n\n#### ОСКОЛОК СОЗИДАНИЯ\n\n**Умение механика 1-го уровня**\n\nВы узнаёте, как изготовить осколок созидания, который представляет собой крошечный магический предмет со множеством применений, который появляется на вас. В своём базовом состоянии осколок предстаёт в виде постоянно меняющегося, жидкообразного сгустка плазмы.\n\nОсколок мгновенно исчезает, если вы убиты или если он не находится в вашем распоряжении более 24 часов подряд. Если осколок уничтожен или вы потеряете его, вы можете совершить 1-часовой ритуал, чтобы создать замену. Этот ритуал можно выполнить как часть короткого или продолжительного отдыха.\n\nУ осколка есть количество зарядов, равное вашему модификатору ИНТ (минимум 1), и вы восстанавливаете все израсходованные заряды, когда заканчиваете продолжительный отдых. Заряды можно тратить на активацию следующих свойств.\n\n##### Вдохновить\n\nКогда вы совершаете проверку характеристики, касаясь осколка (независимо от его текущей формы), вы можете потратить 1 заряд, чтобы бросить d6 и добавить выпавшее число к результату вашей проверки.\n\n##### Преобразовать\n\nКасаясь осколка, вы можете действием преобразовать его в любой тип немагического оружия или щита или в любой объект Среднего размера или меньше. Объект появляется в незанятом пространстве в пределах 10 футов от вас, но выбранное пространство должно содержать поверхность или жидкость, способную поддерживать объект. Если созданный вами объект имеет подходящий размер, чтобы его можно было носить или держать, вы можете выбрать, чтобы объект появился в вашей руке или на вас. Общая стоимость (в золотых монетах) созданного объекта не может превышать 20 × ваш уровень механика.\n\nПреобразованный осколок остаётся в своей новой форме до тех пор, пока вы не умрёте, не используете действие, чтобы вернуть его в исходное состояние, или не используете действие, чтобы преобразовать его снова. Независимо от того, какую форму принимает осколок, те, кто обращается с осколком, могут почувствовать что-то странное в его природе. Осколок нельзя выдать за типичный предмет для целей покупки и продажи.\n\n#### ПРОГРЕССИЯ МЕХАНИКА\n\n| УРОВЕНЬ | БМ | ИЗВЕСТНО ЭФФЕКТОВ УЛУЧШЕНИЯ | УЛУЧШЕННЫЕ ПРЕДМЕТЫ | УМЕНИЯ |\n|---|---|---|---|---|\n| 1-й | +2 | — | — | Глаза Творца, Осколок Созидания |\n| 2-й | +2 | 2 | 3 | Улучшение, Эффективное действие |\n| 3-й | +2 | 3 | 3 | Подкласс механика |\n| 4-й | +2 | 3 | 3 | Улучшение |\n| 5-й | +3 | 4 | 4 | Мультиатака (2/Действие \"Атака\") |\n| 6-й | +3 | 4 | 4 | Быстрое улучшение |\n| 7-й | +3 | 5 | 4 | Особенность подкласса |\n| 8-й | +3 | 5 | 4 | Улучшение |\n| 9-й | +4 | 6 | 5 | Великое созидание |\n| 10-й | +4 | 6 | 5 | Героическое благословение |\n| 11-й | +4 | 6 | 5 | Особенность подкласса |\n| 12-й | +4 | 7 | 5 | Улучшение |\n| 13-й | +5 | 7 | 6 | Интуиция инженера |\n| 14-й | +5 | 7 | 6 | Дальнее улучшение |\n| 15-й | +5 | 8 | 6 | Особенность подкласса |\n| 16-й | +5 | 8 | 6 | Улучшение |\n| 17-й | +6 | 8 | 7 | Всегда готов |\n| 18-й | +6 | 9 | 7 | Совершенное созидание |\n| 19-й | +6 | 9 | 7 | Улучшение |\n| 20-й | +6 | 9 | 7 | Эпическое благословение |\n\n#### УЛУЧШЕНИЕ\n\n**Умение механика 2-го уровня**\n\nВы получаете способность направлять магическую энергию в предметы. Чтобы использовать эту способность, вы должны потратить 1 час, сосредотачиваясь на предмете, который хотите улучшить, оставаясь при этом в физическом контакте с ним (что можно сделать как часть короткого или продолжительного отдыха).\n\nВы получаете два эффекта улучшения по вашему выбору. Варианты эффектов улучшения подробно описаны в конце описания класса. На определённых уровнях механика вы получаете дополнительные эффекты улучшения по своему выбору, как показано в столбце \"Известно эффектов улучшения\" таблицы прогрессии механика.\n\nКогда вы используете эту способность, выберите эффект из тех, которые вы знаете. Независимо от эффекта, улучшенный предмет считается магическим предметом, пока эффект остаётся активным. Вы можете применять эти эффекты к существующим магическим предметам, и любые бонусы или особенности, предоставляемые эффектом улучшения, складываются с любыми свойствами, которыми магический предмет уже обладает.\n\nЕсли не указано иное, выбранный эффект длится неопределённо долго, но в качестве действия вы можете коснуться предмета, чтобы прекратить текущий эффект, который вы создали. Вы можете иметь активные эффекты на нескольких предметах, при условии, что вы потратите необходимое время, сосредотачиваясь на каждом предмете индивидуально. Однако предмет может нести только один эффект за раз. Многократное использование одного и того же эффекта не складывается.\n\nМаксимальное количество предметов, на которые вы можете воздействовать с помощью этой особенности одновременно, указано в столбце \"Улучшенные предметы\" таблицы прогрессии механика. Если вы попытаетесь превысить свой максимум, вы должны выбрать, какой текущий эффект прекратить.\n\nВы также можете улучшить свой преобразованный осколок созидания, при условии, что его форма соответствует требованиям выбранного эффекта. Эффект остаётся с осколком при его преобразовании до тех пор, пока новая форма остаётся совместимой — если нет, эффект немедленно прекращается.\n\n#### ЭФФЕКТИВНОЕ ДЕЙСТВИЕ\n\n**Умение механика 2-го уровня**\n\nВаш механический опыт позволяет вам использовать предметы более эффективно в хаосе битвы. Вы можете использовать бонусное действие, чтобы совершить действие \"Использовать объект\" или выполнить опцию оружия.\n\n#### УМЕНИЯ ПОДКЛАССА МЕХАНИКА\n\n**Умение механика 3-го, 7-го, 11-го и 15-го уровней*\n\nВыберите подкласс, который отражает ваши отношения с вашим ремеслом, либо Металлург, либо Заклинатель (подробно описаны в конце этого класса). Ваш выбор предоставляет вам особенности на 3-м, 7-м, 11-м и 15-м уровнях.\n\n#### УЛУЧШЕНИЕ\n\n**Умение механика 4-го, 8-го, 12-го, 16-го и 19-го уровней*\n\nВыберите одно из следующих улучшений (значения характеристик не могут быть повышены выше 20 с помощью этой особенности):\n\n* Увеличьте одну характеристику на 2.\n* Увеличьте две разные характеристики на 1 каждую.\n* Увеличьте одну характеристику на 1 и выберите талант либо из воинских, либо из технических талантов.\n\n#### МУЛЬТИАТАКА\n\n**Умение механика 5-го уровня**\n\nВаше физическое мастерство возросло. В свой ход вы можете совершить две атаки, когда совершаете действие \"Атака\".\n\n#### БЫСТРОЕ УЛУЧШЕНИЕ\n\n**Умение механика 6-го уровня**\n\nТеперь вы можете использовать свою особенность \"Улучшение\" быстрее. В качестве бонусного действия вы можете коснуться предмета и наделить его известным эффектом улучшения по вашему выбору. Вы по-прежнему связаны всеми другими ограничениями особенности \"Улучшение\", включая количество предметов.\n\nВы можете использовать свою особенность \"Быстрое улучшение\" количество раз, равное вашему модификатору ИНТ, и восстанавливаете все израсходованные использования, когда заканчиваете продолжительный отдых.\n\n#### ВЕЛИКОЕ СОЗИДАНИЕ\n\n**Умение механика 9-го уровня**\n\nВаше растущее понимание природы реальности позволяет вам лучше контролировать свою особенность \"Осколок Созидания\". Вы получаете следующие улучшения его заданных свойств.\n\n##### Вдохновить\n\nВаш бонус к проверкам характеристик теперь составляет 1d8 (вместо 1d6).\n\n##### Преобразовать\n\nТеперь вы можете преобразовать осколок в любой инструмент или немагический предмет Большого размера или меньше. Все остальные ограничения по-прежнему применяются, включая ограничение по стоимости в золотых монетах.\n\n#### ГЕРОИЧЕСКОЕ БЛАГОСЛОВЕНИЕ\n\n**Умение механика 10-го уровня**\n\nВаша приверженность пути механика дарует вам мощную новую способность. Выберите одно из следующих героических благословений:\n\n* **Проклятие Разрушения.** В качестве действия вы можете совершить атаку заклинанием ближнего боя, используя свой модификатор атаки улучшения (см. Эффекты улучшения) против существа или предмета в пределах досягаемости. При успешном попадании цель становится проклятой, так что она уязвима ко всему урону. Если цель является существом, оно может попытаться совершить спасение ТЕЛ против вашего СЛ спасения от улучшения (см. Эффекты улучшения) каждый раз, когда получает новый урон, прекращая проклятие при успехе. После того, как вы используете эту особенность, вы должны завершить продолжительный отдых, прежде чем сможете использовать её снова.\n* **Починка Сломанного.** В качестве действия вы касаетесь существа или предмета и магически заставляете его восстановить количество хитов, равное 5 × ваш уровень механика. Этот эффект также восстанавливает любые катастрофические повреждения, полученные целью, такие как потерянные конечности, отсутствующие части или другие повреждения, которые обычно были бы непоправимы. Если предмет не имеет общего количества хитов, ваше прикосновение восстанавливает его работоспособность настолько хорошо, насколько это возможно с доступными частями. Эта особенность не может восстановить израсходованные заряды на магических предметах или восстановить магические свойства немагическим предметам, которые когда-то были магическими. После того, как вы используете эту особенность, вы должны завершить продолжительный отдых, прежде чем сможете использовать её снова.\n\n#### ИНТУИЦИЯ ИНЖЕНЕРА\n\n**Умение механика 13-го уровня**\n\nПока вы уделяете задаче хотя бы 1 минуту непрерывного внимания, когда вы совершаете проверку характеристики, относитесь к любому броску d20 9 или ниже так, как если бы вы бросили 10.\n\nНормальная деятельность, такая как перемещение, не прерывает сосредоточенность, но атака, получение урона или участие во всём, что требует порядка инициативы, прерывает сосредоточенность.\n\n#### ДАЛЬНЕЕ УЛУЧШЕНИЕ\n\n**Умение механика 14-го уровня**\n\nТеперь вы можете использовать свою особенность \"Быстрое улучшение\" на предметах, которые вы видите в пределах 60 футов от вас. (Вам больше не нужно касаться их.)\n\nКроме того, если эффект от вашей особенности \"Улучшение\" обычно требует от вас касания предмета для активации его свойств, вам больше не нужно этого делать, пока предмет находится в пределах 60 футов от вас. Вам не нужно видеть предмет, чтобы активировать его свойства таким образом.\n\n#### ВСЕГДА ГОТОВ\n\n**Умение механика 17-го уровня**\n\nКогда вы должны получить урон от атаки, вы можете использовать реакцию, чтобы совершить действие \"Использовать объект\".\n\n#### СОВЕРШЕННОЕ СОЗИДАНИЕ\n\n**Умение механика 18-го уровня**\n\nВаше растущее понимание природы реальности позволяет вам лучше контролировать свою особенность \"Осколок Созидания\". Вы получаете следующие улучшения его заданных свойств.\n\n##### Вдохновить\n\nВаш бонус к проверкам характеристик теперь составляет 1d10 (вместо 1d8).\n\n##### Преобразовать\n\nТеперь вы можете преобразовать осколок в любой предмет — включая сооружения и транспортные средства — Огромного размера или меньше. Вы больше не связаны никакими ограничениями по стоимости при выборе формы.\n\n#### ЭПИЧЕСКОЕ БЛАГОСЛОВЕНИЕ\n\n**Умение механика 20-го уровня**\n\nВаша приверженность пути механика дарует вам мощную новую способность. Вы получаете следующее эпическое благословение:\n\n* **Творческий Движок.** Вы получаете бонус +1 к своим спасениям за каждый эффект от вашей особенности \"Улучшение\", в настоящее время активный на предметах в пределах 60 футов от вас. Если вы проваливаете спасение, пока какой-либо из этих предметов находится в пределах 60 футов от вас, вы можете автоматически прекратить один из этих эффектов (по вашему выбору), чтобы вместо этого преуспеть в спасении.\n\n#### ЭФФЕКТЫ УЛУЧШЕНИЯ\n\nВ этом разделе перечислены эффекты, доступные механикам для изучения и использования со своей особенностью \"Улучшение\". В каждом варианте указан тип предмета, необходимый для функционирования эффекта, и приведено описание того, как работает эффект. Любые эффекты, которые требуют действия для активации своих свойств, могут быть активированы с помощью действия \"Использовать объект\".\n\nНекоторые эффекты требуют от вас совершения броска атаки или требуют, чтобы ваша цель совершила спасение. Бонус атаки и СЛ спасения для этого рассчитываются следующим образом:\n\n*СЛ спасения от улучшения = 8 + ваш бонус мастерства (БМ) + ваш модификатор Интеллекта (ИНТ)*\n\n*Модификатор атаки улучшения = ваш бонус мастерства (БМ) + ваш модификатор Интеллекта (ИНТ)*\n\n##### КЛЕЙКИЙ\n\n*Требование к предмету: Большое или меньшее оборудование или объект, который не носят и не держат*\n\nВы наделяете предмет способностью прилипать к поверхностям. Пока предмет находится в пределах 30 футов от вас, вы можете действием произнести кодовое слово и прикрепить предмет к твёрдой поверхности, к которой он прикасается. Выбранная поверхность не может быть частью существа.\n\nБудучи прикреплённым, предмет может выдержать вес до 1000 фунтов. Если добавляется дополнительный вес, предмет отрывается от поверхности (падая или двигаясь соответствующим образом).\n\nСущество может потратить действие, чтобы попытаться удалить прикреплённый предмет с помощью проверки СИЛ (Атлетика). СЛ для этой проверки равна 8 + ваш БМ + ваш модификатор ИНТ. Если существо преуспевает в этой проверке, предмет отрывается от поверхности.\n\nЕсли предмет не отрывается силой, он остаётся прикреплённым в течение 24 часов или пока вы не используете действие, чтобы отсоединить его. Если предмет отрывается каким-либо способом, его адгезионные свойства нельзя активировать снова, пока вы не завершите продолжительный отдых.\n\n##### СКЛАДНОЙ\n\n*Требование к предмету: Большой или меньший предмет, который не носят, не держат и не закрепляют на месте*\n\nВы наделяете предмет способностью становиться меньше. Касаясь предмета, вы можете действием уменьшить его размер. Когда вы это делаете, размер цели уменьшается вдвое во всех измерениях, её вес уменьшается до 1/8 от нормального, и она уменьшает свою категорию размера на одну, например, с Большого до Маленького. Размер цели нельзя уменьшить дальше многократным использованием этой особенности. В качестве действия вы можете коснуться цели и заставить её вернуться к своему первоначальному размеру.\n\n##### ОБНАРУЖИВАЮЩИЙ\n\n*Требование к предмету: Очки, очки, подзорная труба или подобное оборудование или объект с прозрачной поверхностью*\n\nВы наделяете предмет магическими возможностями для улучшения восприятия. Касаясь предмета, вы можете действием активировать один из перечисленных эффектов. Вы должны экипировать, носить или активно смотреть через улучшенный предмет, чтобы получить выгоду от выбранного эффекта:\n\n* **Тёмное зрение.** Вы получаете тёмное зрение на расстояние до 30 футов.\n* **Невидимое зрение.** Вы можете видеть невидимых существ и предметы, как если бы они были видимыми. Вы также осведомлены о любых существах в пределах 30 футов от вас или о том, что какие-либо существа входят в пределы 30 футов от вас, независимо от условий освещения.\n* **Магическое зрение.** Вы получаете преимущества заклинания \"обнаружение магии\" в пределах 30 футов от вас.\n* **Рентгеновское зрение.** Вы получаете возможность видеть сквозь твёрдый материал в пределах 30 футов от вас. Для вас твёрдые предметы в этом радиусе кажутся прозрачными и не мешают прохождению света через них. Зрение может проникать сквозь 1 фут камня, 1 дюйм обычного металла или до 3 футов дерева или грязи. Более толстые вещества блокируют ваше зрение, как и тонкий лист свинца.\n\nПока улучшенный предмет активирован, вы можете действием деактивировать его или переключить тип зрения, которое даёт предмет. Вы можете держать предмет активированным до 1 минуты, все сразу или за несколько более коротких периодов, каждый из которых использует минимум 6 секунд (1 раунд) из продолжительности. Эффект полностью перезаряжается, когда вы заканчиваете продолжительный отдых.\n\n*На более высоких уровнях.* Когда вы достигнете 9-го уровня в классе механика, дальность действия всех эффектов зрения увеличивается до 60 футов.\n\n##### НАДЕЛЁННЫЙ СИЛОЙ\n\n*Требование к предмету: Оружие*\n\nВы наделяете оружие наступательной силой. Оружие получает бонус +1 к броскам атаки и урона. Если оно ещё не было магическим, то теперь оно магическое. Если оно уже было магическим, этот бонус складывается с любыми существующими бонусами.\n\n*На более высоких уровнях.* Когда вы достигнете 9-го уровня в классе механика, бонус к атаке и урону увеличивается до +2. На 15-м уровне он становится +3.\n\n##### ИЛЛЮЗОРНЫЙ\n\n*Требование к предмету: Большой или меньший предмет*\n\nВы наделяете предмет способностью маскировать свой истинный облик. Касаясь цели, вы можете действием заставить предмет выглядеть как другой предмет того же размера и общего состава. Вы не можете использовать эту особенность, чтобы изменить общую природу цели. Например, транспортное средство всегда должно выглядеть как другой вид транспортного средства, а оборудование должно выглядеть как какой-то другой вид оборудования. В противном случае степень иллюзии зависит от вас.\n\nИзменение внешнего вида не выдерживает физического осмотра. Например, если вы используете этот эффект, чтобы сделать заточенный меч тусклым, любой, кто коснётся лезвия, пострадает, как если бы они коснулись острого лезвия.\n\nЧтобы определить, замаскирован ли предмет, существо может использовать своё действие для осмотра предмета и должно преуспеть в проверке ИНТ (Расследование) против вашего СЛ спасения от улучшения.\n\n*На более высоких уровнях.* Когда вы достигнете 9-го уровня в классе механика, вы можете воздействовать на Огромные или меньшие предметы.\n\n##### ЗАГРУЗОЧНЫЙ\n\n*Требование к предмету: Оружие со свойством \"Боеприпасы\"*\n\nВы наделяете предмет способностью вызывать магические боеприпасы. Когда вы владеете оружием, соответствующий боеприпас магически появляется на месте, когда вы атакуете. Любой урон, нанесённый этим боеприпасом, считается магическим.\n\nЕсли вы используете этот эффект на оружии со свойством \"Зарядка\", вам не нужно тратить время на перезарядку оружия.\n\n##### ФОСФОРЕСЦИРУЮЩИЙ\n\n*Требование к предмету: Маленький или меньший предмет, который можно носить или держать*\n\nВы наделяете предмет способностью светиться. Пока предмет находится на вас, вы можете действием заставить предмет испускать яркий свет в радиусе 20 футов и тусклый свет на дополнительные 20 футов. Когда вы впервые активируете предмет, вы можете выбрать, светит ли этот свет нормально или его могут видеть только количество существ по вашему выбору в пределах 30 футов от вас. Максимальное количество существ, которых вы можете включить, равно вашему модификатору ИНТ. Свет может быть любого цвета, который вы выберете.\n\nВы можете заставить предмет прекратить излучение света в любой момент (никаких действий не требуется).\n\n*На более высоких уровнях.* Когда вы достигнете 9-го уровня в классе механика, радиус увеличивается до яркого света в радиусе 30 футов и тусклого света на дополнительные 30 футов. Вы можете выбрать, чтобы яркий свет был солнечным светом.\n\n##### ДВИЖУЩИЙ\n\n*Требование к предмету: Доспехи (не щиты) или Маленький или меньший предмет, который можно носить*\n\nВы наделяете предмет способностью увеличивать скорость владельца. Во время ношения улучшенного предмета ваша базовая скорость передвижения увеличивается на 5 футов.\n\nКроме того, во время ношения предмета вы можете действием перемещаться по вертикали до 10 футов и оставаться подвешенным там до 1 минуты. Вы можете повторить это действие в последующие ходы, поднимаясь до дополнительных 10 футов каждый раз, когда вы это делаете.\n\nНаходясь в подвешенном состоянии, вы можете двигаться только толкаясь или подтягиваясь к закреплённому предмету или поверхности в пределах досягаемости (например, стена или потолок), что позволяет вам двигаться, как если бы вы карабкались. Когда этот эффект заканчивается или вы решаете прекратить его (никаких действий не требуется), вы плавно опускаетесь на землю, если вы всё ещё находитесь в воздухе, и вы не можете активировать этот эффект улучшения снова, пока не завершите продолжительный отдых.\n\n*На более высоких уровнях.* Когда вы достигнете 9-го уровня в классе механика, бонус к скорости передвижения увеличится до 10 футов. На 15-м уровне он станет 20 футов.\n\n##### ПРОТЕИЧЕСКИЙ\n\n*Требование к предмету: Оружие*\n\nВы наделяете оружие способностью изменять тип своего урона. Когда вы успешно наносите урон улучшенным оружием, вы можете заменить тип урона оружия другим типом по вашему выбору. Урон, изменённый таким образом, всегда считается магическим для целей преодоления сопротивлений и иммунитетов.\n\nВы можете использовать этот эффект улучшения количество раз, равное вашему БМ, и восстанавливаете все израсходованные использования, когда заканчиваете продолжительный отдых.\n\n##### РЕАКТИВНЫЙ\n\n*Требование к предмету: Большой или меньший предмет, который не носят, не держат и не закрепляют на месте*\n\nВы наделяете предмет способностью обнаруживать определённые триггеры и реагировать одним из нескольких способов. Касаясь предмета, вы можете действием установить или изменить триггер и реакцию предмета.\n\nВы можете настроить предмет так, чтобы он срабатывал, когда определённое вами существо приближается к нему на расстояние 30 футов. Это может быть конкретное существо, с которым вы встречались, например, \"Джон посыльный\", общее визуальное описание, например, \"любой, кто носит униформу городской стражи\", или тип существа, например, \"Небожители\". Ваш ГМ имеет последнее слово в том, что разумно для триггера.\n\nПри срабатывании вы мгновенно осознаёте, что предмет сработал, и предмет может отреагировать одним из следующих способов. По усмотрению вашего ГМа, предмет может реагировать и другими сопоставимыми способами:\n\n* **Запись.** Предмет начинает записывать всё, что он может \"видеть\" и \"слышать\" в пределах 60 футов от него в течение следующего часа, воспринимая как существо с типичным зрением или слухом могло бы. Через 1 час предмет прекращает запись новой информации и сохраняет запись до тех пор, пока предмет больше не будет улучшен или пока вы не используете действие для установки нового триггера или реакции. Пока запись сохранена, вы или любое существо по вашему выбору можете коснуться предмета, чтобы мысленно видеть и слышать всё, что содержится в записи.\n* **Звук.** Предмет издаёт звук в течение 1 минуты, который можно услышать на расстоянии до 60 футов (вы выбираете качество и диапазон), например, звук звенящих колоколов или набор птичьих голосов. В качестве альтернативы, вы можете заставить его издать предопределённое сообщение из 25 слов или меньше своим собственным голосом.\n\n*На более высоких уровнях.* Когда вы достигнете 9-го уровня в классе механика, предмет может реагировать, когда указанное существо приближается к нему на расстояние 60 футов.\n\n##### УСИЛЕННЫЙ\n\n*Требование к предмету: Предмет с Хитами*\n\nВы укрепляете предмет. Хиты цели и максимум хитов увеличиваются на величину, равную 5 × ваш уровень механика. Если предмет уничтожен, пока этот эффект активен, эффект заканчивается.\n\n##### ВОЗВРАЩАЮЩИЙ\n\n*Цель: Оборудование или Объект, который может поместиться в руке и не надевается и не держится*\n\nВы наделяете предмет способностью возвращаться в вашу руку. Пока улучшенный предмет находится в пределах 60 футов, вы можете заставить его мгновенно телепортироваться в вашу руку (действия не требуется). У вас должна быть хотя бы одна свободная рука, чтобы эта способность функционировала.\n\n*На более высоких уровнях.* Когда вы достигнете 9-го уровня в классе механика, вы можете воздействовать на предмет на расстоянии до 120 футов от вас. На 15-м уровне вы можете воздействовать на предмет в любом месте на той же плоскости, что и вы.\n\n##### ОТТАЛКИВАЮЩИЙ\n\n*Требование к предмету: Щит*\n\nВы наделяете предмет способностью отталкивать нападающих. Когда существо Большого размера или меньше попадает в вас атакой ближнего боя, вы можете использовать свою реакцию, чтобы заставить цель совершить спасение СИЛ против вашего СЛ спасения от улучшения. При провале существо отталкивается на 15 футов от вас. Если существо сталкивается с твёрдой поверхностью (например, стеной), прежде чем переместиться на полное расстояние, оно получает 1d6 дробящего урона за каждые 10 футов, на которые оно переместилось.\n\n*На более высоких уровнях.* Когда вы достигнете 9-го уровня в классе механика, цель, провалившая свой спасбросок, отталкивается на 30 футов от вас.\n\n##### МИСТИЧЕСКИЙ МЕТАЛЛ\n\n**Умение Металлурга 3-го уровня**\n\nВы учитесь преобразовывать доспехи в мистическую форму. Если вы потратите 1 час непрерывного сосредоточения, контактируя с немагическим комплектом доспехов (что можно сделать как часть короткого или продолжительного отдыха), вы можете преобразовать эти доспехи в комплект мистического металла. Преобразование длится до тех пор, пока вы не решите прекратить его или пока вы не используете эту особенность для преобразования другого комплекта доспехов.\n\nЛюбые текущие эффекты от вашей особенности \"Улучшение\" на доспехах автоматически прекращаются, когда доспехи возвращаются в своё обычное состояние. Если кто-либо, кроме вас, попытается надеть мистический металл, он мгновенно вернётся в своё обычное состояние.\n\nПосле преобразования мистический металл напоминает комплект металлических доспехов с головы до пят, но вы выбираете его цвет, стиль и другие косметические детали. Независимо от внешнего вида, доспехи из мистического металла не сделаны из природных материалов, таких как металл или дерево. Поэтому на них не воздействует магия, например, заклинание \"нагревание металла\" или способности, подобные способности ржавого монстра.\n\nМистический металл лёгок и не мешает движению, и вы считаетесь владеющим им.\n\nВаш мистический металл функционирует как магический комплект доспехов со следующими свойствами:\n\n* Каждая перчатка доспехов функционирует как простое оружие ближнего боя со свойством \"Лёгкое\" (которым вы владеете). Вы можете выбрать, использовать ли свой модификатор СИЛ или ИНТ для определения бонуса атаки и урона, наносимого перчатками. При успешном попадании перчатка наносит 1d6 + ваш модификатор СИЛ или ИНТ (по вашему выбору) магического дробящего урона.\n* Если он находится на той же плоскости, что и вы, вы можете использовать бонусное действие, чтобы призвать доспехи. Когда вы это делаете, вы выбираете, появится ли доспех в незанятом пространстве в пределах 5 футов от вас или появится на вас, полностью надетым. Если вы уже носите доспехи, когда призываете доспехи из мистического металла, они не могут появиться на вас.\n* Находясь в ношении, доспехи прикреплены к вашему телу и не могут быть сняты против вашей воли.\n* Во время ношения доспехов ваш КД равен 13 + ваш модификатор ИНТ.\n\nСущества, которые обращаются с мистическим металлом или осматривают его, могут сказать, что это не настоящий магический предмет. В противном случае он следует правилам типичного магического предмета.\n\n### ПОДКЛАСС: МЕТАЛЛУРГ\n\nМеханики, которые стремятся к ремеслу Металлурга, наслаждаются острыми ощущениями от боя и спроектированных вооружений. Творения Металлурга внушают трепет в бою, хотя мало кто из врагов живёт, чтобы распространять истории о своих ужасающих металлических механизмах.\n\n#### ПРОГРЕССИЯ МЕТАЛЛУРГА\n\n| УРОВЕНЬ МЕХАНИКА | УМЕНИЯ |\n|---|---|\n| 3-й | Улучшение: Поглощающий, Мистический металл |\n| 7-й | Сильный Удар (d6) |\n| 9-й | Сильный Удар (d8), Джаггернаут |\n| 15-й | Цельнометаллический, Сильный Удар (d10) |\n\n#### УЛУЧШЕНИЕ: ПОГЛОЩАЮЩИЙ\n\n**Умение Металлурга 3-го уровня**\n\nВы получаете следующий уникальный эффект для своей особенности \"Улучшение\". Этот эффект нельзя заменить, и он не учитывается в количестве известных вами эффектов, как показано в столбце \"Известно эффектов улучшения\" таблицы прогрессии механика.\n\n##### Поглощающий\n\n*Требование к предмету: Доспехи или Щит*\n\nВы наделяете доспехи или щит способностью поглощать и адаптироваться к различным типам урона. Когда вы получаете единичный урон от кислоты, холода, огня, силы, молнии, яда или грома, надевая или владея предметом, вы можете использовать свою реакцию, чтобы уменьшить полученный урон на величину, равную удвоенному вашему модификатору ИНТ. Затем вы получаете сопротивление вызвавшему урон типу на 1 минуту или до тех пор, пока вы не используете эту особенность для поглощения другого типа урона.\n\nВы можете использовать эту особенность количество раз, равное вашему БМ, восстанавливая все израсходованные заряды, когда заканчиваете продолжительный отдых.\n\n#### СИЛЬНЫЙ УДАР\n\n**Умение Металлурга 7-го уровня**\n\nВы учитесь улучшать наступательные возможности своей особенности \"Мистический Металл\". Во время ношения доспехов вы получаете следующие преимущества:\n\n* Когда вы наносите урон атакой оружием, вы наносите дополнительный 1d6 урона от силы. Этот дополнительный урон увеличивается на более высоких уровнях, становясь 1d8 на 9-м уровне и 1d10 на 15-м уровне.",
  "hitDie": "d10",
  "savingThrows": [
    "ТЕЛ",
    "ИНТ"
  ],
  "proficiencies": {
    "skills": {
      "granted": [],
      "choose": 2,
      "from": [
        "Магия",
        "История",
        "Расследование",
        "Внимательность",
        "Ловкость рук"
      ]
    },
    "armor": [
      "Лёгкие доспехи",
      "средние доспехи",
      "щиты"
    ],
    "weapons": [
      "Простое оружие",
      "воинское оружие"
    ],
    "tools": [
      "Инструменты механика",
      "два дополнительных инструмента на ваш выбор"
    ]
  },
  "startingEquipment": {
    "items": [
      "(a) воинское оружие и щит или (b) два простых оружия.",
      "Лёгкий арбалет и 20 болтов.",
      "(a) чешуйчатый доспех или (b) кожаный доспех.",
      "Инструменты механика и набор исследователя подземелий."
    ]
  },
  "levels": [
    {
      "level": 1,
      "proficiencyBonus": "+2",
      "features": [
        "Глаза Создателя",
        "Осколок Творения"
      ]
    },
    {
      "level": 2,
      "proficiencyBonus": "+2",
      "features": [
        "Аугментация",
        "Эффективное Действие"
      ]
    },
    {
      "level": 3,
      "proficiencyBonus": "+2",
      "features": [
        "Подкласс Механиста"
      ]
    },
    {
      "level": 4,
      "proficiencyBonus": "+2",
      "features": [
        "Улучшение"
      ]
    },
    {
      "level": 5,
      "proficiencyBonus": "+3",
      "features": [
        "Мультиатака (2/Действие Атаки)"
      ]
    },
    {
      "level": 6,
      "proficiencyBonus": "+3",
      "features": [
        "Быстрая Аугментация"
      ]
    },
    {
      "level": 7,
      "proficiencyBonus": "+3",
      "features": [
        "Особенность Подкласса"
      ]
    },
    {
      "level": 8,
      "proficiencyBonus": "+3",
      "features": [
        "Улучшение"
      ]
    },
    {
      "level": 9,
      "proficiencyBonus": "+4",
      "features": [
        "Великое Творение"
      ]
    },
    {
      "level": 10,
      "proficiencyBonus": "+4",
      "features": [
        "Героический Дар"
      ]
    },
    {
      "level": 11,
      "proficiencyBonus": "+4",
      "features": [
        "Особенность Подкласса"
      ]
    },
    {
      "level": 12,
      "proficiencyBonus": "+4",
      "features": [
        "Улучшение"
      ]
    },
    {
      "level": 13,
      "proficiencyBonus": "+5",
      "features": [
        "Проницательность Инженера"
      ]
    },
    {
      "level": 14,
      "proficiencyBonus": "+5",
      "features": [
        "Дальняя Аугментация"
      ]
    },
    {
      "level": 15,
      "proficiencyBonus": "+5",
      "features": [
        "Особенность Подкласса"
      ]
    },
    {
      "level": 16,
      "proficiencyBonus": "+5",
      "features": [
        "Улучшение"
      ]
    },
    {
      "level": 17,
      "proficiencyBonus": "+6",
      "features": [
        "Всегда Готов"
      ]
    },
    {
      "level": 18,
      "proficiencyBonus": "+6",
      "features": [
        "Совершенное Творение"
      ]
    },
    {
      "level": 19,
      "proficiencyBonus": "+6",
      "features": [
        "Улучшение"
      ]
    },
    {
      "level": 20,
      "proficiencyBonus": "+6",
      "features": [
        "Эпический Дар"
      ]
    }
  ],
  "features": [],
  "subclasses": [],
  "type": "class",
  "id": "BFRD:class/mehanik",
  "slug": "mehanik",
  "name": "МЕХАНИК",
  "schemaVersion": "1.0.0",
  "src": {
    "abbr": "BFRD",
    "name": "Black Flag Reference Document",
    "version": "1.0",
    "url": "https://bfrd.net/",
    "license": "Open RPG Creative License (ORC)",
    "hash": "551fcef425382629e6898f587cecc13cc1b96a777517acac5a23a73af19aa17e"
  },
  "summary": "Как механик, вы обладаете следующими особенностями класса.",
  "sourceFile": "input/classes/mechanist.md"
}