{
  "description": "### КЛАССОВЫЕ УМЕНИЯ\n\nКак монах, вы обладаете следующими особенностями класса.\n\n#### ХИТЫ\n\n* **Кость хитов:** 1d8 за уровень монаха.\n* **Хиты на 1-м уровне:** 8 + ваш модификатор ТЕЛ.\n* **Хиты на более высоких уровнях:** 1d8 (или 5) + ваш модификатор ТЕЛ за каждый уровень монаха после 1-го.\n\n#### ВЛАДЕНИЯ\n\n* **Доспехи:** Нет.\n* **Оружие:** Простое оружие, короткие мечи.\n* **Инструменты:** Один на ваш выбор.\n* **Спасброски:** СИЛ, ЛОВ.\n* **Навыки:** Выберите два из следующих: Акробатика, Атлетика, История, Проницательность, Религия и Скрытность.\n\n#### НАЧАЛЬНОЕ СНАРЯЖЕНИЕ\n\nВы начинаете со следующим снаряжением, в дополнение к снаряжению, предоставленному вашей предысторией:\n\n* (a) любое простое оружие.\n* (a) набор исследователя подземелий или (b) набор исследователя.\n* (a) 10 дротиков или (b) праща.\n\n#### ПРОГРЕССИЯ МОНАХА\n\n| УРОВЕНЬ | БМ | УРОН БОЕВЫХ ИСКУССТВ | ОЧКИ ТЕХНИК | ДВИЖЕНИЕ БЕЗ ДОСПЕХОВ | УМЕНИЯ |\n|---|---|---|---|---|---|\n| 1-й | +2 | 1d4 | — | — | Боевые искусства, Защита без доспехов |\n| 2-й | +2 | 1d4 | 3 | +10 фт | Техники, Движение без доспехов |\n| 3-й | +2 | 1d4 | 5 | +10 фт | Подкласс Монаха |\n| 4-й | +2 | 1d4 | 5 | +10 фт | Улучшение |\n| 5-й | +3 | 1d6 | 6 | +10 фт | Мультиатака (2/Действие Атаки), Оглушающий удар |\n| 6-й | +3 | 1d6 | 7 | +15 фт | Усиленные удары, Уклонение |\n| 7-й | +3 | 1d6 | 8 | +15 фт | Особенность Подкласса |\n| 8-й | +3 | 1d6 | 9 | +15 фт | Улучшение |\n| 9-й | +4 | 1d6 | 9 | +15 фт | Совершенное движение |\n| 10-й | +4 | 1d6 | 10 | +20 фт | Героический дар |\n| 11-й | +4 | 1d8 | 11 | +20 фт | Особенность Подкласса |\n| 12-й | +4 | 1d8 | 12 | +20 фт | Улучшение |\n| 13-й | +5 | 1d8 | 13 | +20 фт | Астральные учения |\n| 14-й | +5 | 1d8 | 14 | +25 фт | Алмазная душа |\n| 15-й | +5 | 1d8 | 15 | +25 фт | Особенность Подкласса |\n| 16-й | +5 | 1d8 | 16 | +25 фт | Улучшение |\n| 17-й | +6 | 1d10 | 17 | +25 фт | Безвременное \"я\" |\n| 18-й | +6 | 1d10 | 18 | +30 фт | Пустое тело |\n| 19-й | +6 | 1d10 | 19 | +30 фт | Улучшение |\n| 20-й | +6 | 1d10 | 20 | +30 фт | Эпический дар |\n\n#### БОЕВЫЕ ИСКУССТВА\n\n**Умение монаха 1-го уровня**\n\nВы мастерски владеете боевыми стилями, в которых используются безоружные удары и оружие монаха, которое представляет собой короткие мечи и любое простое оружие ближнего боя, не имеющее свойства \"Двуручное\" или \"Тяжёлое\". Вы получаете следующие преимущества, если безоружны или владеете только оружием монаха и не носите доспехи или щит:\n\n* Вы можете бросать d4 вместо обычного урона от своего безоружного удара или оружия монаха. Эта кость меняется по мере получения вами уровней монаха, как показано в столбце \"Боевые искусства\" таблицы прогрессии монаха.\n* Вы можете использовать ЛОВ вместо СИЛ для бросков атаки и урона своих безоружных ударов и оружия монаха.\n* Когда вы поражены атакой дальнобойным оружием, вы можете использовать свою реакцию, чтобы уменьшить урон, который вы получаете от атаки, на 1d10 + ваш модификатор ЛОВ + ваш уровень монаха. Если вы уменьшаете урон до 0, вы можете поймать снаряд или метательное оружие, если оно достаточно мало, чтобы вы могли держать его в одной руке, и у вас есть хотя бы одна свободная рука. Если вы ловите снаряд таким образом, вы можете совершить дальнобойную атаку с помощью оружия или боеприпаса, которое вы только что поймали, как часть той же реакции. Вы совершаете эту атаку с владением, независимо от ваших владений оружием, и снаряд считается оружием монаха для атаки, с обычной дальностью 20 футов и большой дальностью 60 футов.\n* Когда вы используете действие \"Атака\" с безоружным ударом или оружием монаха в свой ход, вы можете совершить один безоружный удар в качестве бонусного действия. Например, если вы совершаете действие \"Атака\" и атакуете посохом, вы можете также совершить безоружный удар в качестве бонусного действия, если вы уже не совершили бонусное действие в этот ход.\n\n#### ЗАЩИТА БЕЗ ДОСПЕХОВ\n\n**Умение монаха 1-го уровня**\n\nПока вы не носите доспехи и не владеете щитом, ваш КД равен 10 + ваш модификатор ЛОВ + ваш модификатор МДР.\n\n#### ТЕХНИКИ\n\n**Умение монаха 2-го уровня**\n\nВаша тренировка даёт вам доступ к специальным техникам, которые позволяют вам усиливать и манипулировать энергией внутри себя и окружающей среды. Ваша способность использовать эту энергию представлена очками техник. Ваш уровень монаха определяет количество имеющихся у вас очков, как показано в столбце \"Очки техник\" таблицы прогрессии монаха.\n\nВы можете тратить эти очки для подпитки различных техник. Вы начинаете знать три техники: Шквал ударов, Терпеливая защита и Шаг ветра. Вы узнаёте больше особенностей техник по мере получения уровней в этом классе.\n\nВы восстанавливаете израсходованные очки техник, когда заканчиваете короткий или продолжительный отдых. Вы должны потратить не менее 30 минут отдыха на медитацию, чтобы восстановить свои очки техник.\n\nНекоторые из ваших техник требуют, чтобы ваша цель совершила спасение, чтобы противостоять эффектам техники. СЛ спасения рассчитывается следующим образом:\n\n*СЛ спасения от техники = 8 + ваш бонус мастерства (БМ) + ваш модификатор МДР*\n\n##### Шквал ударов\n\nСразу после того, как вы используете действие в свой ход, вы можете потратить 1 очко техники, чтобы совершить два безоружных удара или совершить одну атаку оружием монаха в качестве бонусного действия.\n\n##### Терпеливая защита\n\nВы можете потратить 1 очко техники, чтобы совершить действие \"Уклонение\" в качестве бонусного действия в свой ход.\n\n##### Шаг ветра\n\nВы можете потратить 1 очко техники, чтобы совершить действие \"Отход\" или \"Рывок\" в качестве бонусного действия в свой ход. Когда вы это делаете, расстояние вашего прыжка удваивается до начала вашего следующего хода.\n\n#### ПРОГРЕССИЯ МОНАХА\n\n| УРОВЕНЬ | БМ | БОЕВЫЕ ИСКУССТВА | ОЧКИ ТЕХНИК | ДВИЖЕНИЕ БЕЗ ДОСПЕХОВ | УМЕНИЯ |\n|---|---|---|---|---|---|\n| 1-й | +2 | 1d4 | — | — | Боевые искусства, Защита без доспехов |\n| 2-й | +2 | 1d4 | 3 | +10 футов | Техники, Движение без доспехов |\n| 3-й | +2 | 1d4 | 5 | +10 футов | Подкласс монаха |\n| 4-й | +2 | 1d4 | 5 | +10 футов | Улучшение |\n| 5-й | +3 | 1d6 | 6 | +10 футов | Мультиатака (2/Действие \"Атака\"), Ошеломляющий удар |\n| 6-й | +3 | 1d6 | 7 | +15 футов | Усиленные удары, Уклонение |\n| 7-й | +3 | 1d6 | 8 | +15 футов | Особенность подкласса |\n| 8-й | +3 | 1d6 | 9 | +15 футов | Улучшение |\n| 9-й | +4 | 1d6 | 9 | +15 футов | Безупречное движение |\n| 10-й | +4 | 1d6 | 10 | +20 футов | Героическое благословение |\n| 11-й | +4 | 1d8 | 11 | +20 футов | Особенность подкласса |\n| 12-й | +4 | 1d8 | 12 | +20 футов | Улучшение |\n| 13-й | +5 | 1d8 | 13 | +20 футов | Астральные учения |\n| 14-й | +5 | 1d8 | 14 | +25 футов | Алмазная душа |\n| 15-й | +5 | 1d8 | 15 | +25 футов | Особенность подкласса |\n| 16-й | +5 | 1d8 | 16 | +25 футов | Улучшение |\n| 17-й | +6 | 1d10 | 17 | +25 футов | Безвременное \"Я\" |\n| 18-й | +6 | 1d10 | 18 | +30 футов | Пустое тело |\n| 19-й | +6 | 1d10 | 19 | +30 футов | Улучшение |\n| 20-й | +6 | 1d10 | 20 | +30 футов | Эпическое благословение |\n\n#### ДВИЖЕНИЕ БЕЗ ДОСПЕХОВ\n\n**Умение монаха 2-го уровня**\n\nВаша скорость увеличивается на 10 футов, пока вы не носите доспехи и не владеете щитом. Этот бонус увеличивается, когда вы достигаете определённых уровней монаха, как показано в таблице прогрессии монаха.\n\n#### УМЕНИЯ ПОДКЛАССА МОНАХА\n\n**Умение монаха 3-го, 7-го, 11-го и 15-го уровней*\n\nВыберите подкласс, который отражает ваш метод соединения с энергиями вселенной, либо Мерцающая Тьма, либо Открытая Рука (подробно описаны в конце этого класса). Ваш подкласс предоставляет вам особенности на 3-м, 7-м, 11-м и 15-м уровнях.\n\n#### УЛУЧШЕНИЕ\n\n**Умение монаха 4-го, 8-го, 12-го, 16-го и 19-го уровней*\n\n* Выберите одно из следующих улучшений (значения характеристик не могут быть повышены выше 20 с помощью этой особенности):\n* Увеличьте одну характеристику на 2.\n* Увеличьте две разные характеристики на 1 каждую.\n* Увеличьте одну характеристику на 1 и выберите талант из списка воинских талантов.\n\n#### МУЛЬТИАТАКА\n\n**Умение монаха 5-го уровня**\n\nВаше физическое мастерство возросло. В свой ход вы можете совершить две атаки, когда совершаете действие \"Атака\".\n\n#### ОШЕЛОМЛЯЮЩИЙ УДАР\n\n**Умение монаха 5-го уровня**\n\nВы можете вмешиваться в поток энергии в теле противника. Один раз за ход, когда вы успешно попадаете в другое существо безоружным ударом или оружием монаха, вы можете потратить 1 очко техники, чтобы попытаться оглушить своего противника. Когда вы это делаете, цель получает урон от вашей атаки как обычно, а затем она должна преуспеть в спасении ТЕЛ или быть оглушённой до конца вашего следующего хода. Каждый раз, когда оглушённая цель получает урон, она может повторить спасение, прекращая эффект оглушения при успехе.\n\n#### УСИЛЕННЫЕ УДАРЫ\n\n**Умение монаха 6-го уровня**\n\nВаши безоружные удары считаются магическими для целей преодоления сопротивления и иммунитета к немагическим атакам и урону.\n\n#### УКЛОНЕНИЕ\n\n**Умение монаха 6-го уровня**\n\nВы можете уклоняться от некоторых эффектов области, таких как дыхание синего дракона молнией или заклинание \"огненный шар\". Когда вы подвергаетесь эффекту, который позволяет вам совершить спасение ЛОВ, чтобы получить только половину урона, вы вместо этого не получаете урона, если преуспеваете в спасении, и получаете только половину урона, если проваливаете его.\n\n#### БЕЗУПРЕЧНОЕ ДВИЖЕНИЕ\n\n**Умение монаха 9-го уровня**\n\nПока вы не носите доспехи и не владеете щитом, вы получаете следующие преимущества:\n\n* Когда вы падаете, вы можете использовать свою реакцию, чтобы уменьшить любой урон от падения, который вы бы получили, на величину, равную 5 × ваш уровень монаха.\n* Вы можете перемещаться по вертикальным поверхностям и по жидкостям в свой ход, не падая во время перемещения. Если вы заканчиваете своё перемещение или ваше перемещение прерывается во время стояния на вертикальной поверхности или на жидкости, вы падаете как обычно.\n\n#### ГЕРОИЧЕСКОЕ БЛАГОСЛОВЕНИЕ\n\n**Умение монаха 10-го уровня**\n\nВаша приверженность пути монаха дарует вам мощную новую способность. Выберите одно из следующих героических благословений:\n\n* **Чистота Тела.** Ваше владение энергией, текущей через ваше тело, делает вас невосприимчивым к болезням, урону от яда и отравленному состоянию. Кроме того, когда вы уменьшаетесь до 0 хитов, но не убиты сразу, вы можете мгновенно сбросить общее количество своих хитов до вашего текущего количества очков техник. Вы не можете восстановить хиты таким образом снова, пока не завершите продолжительный отдых.\n* **Чистота Разума.** Ясность вашего разума даёт вам преимущество при спасениях Мудрости. В качестве бонусного действия вы можете прекратить один эффект на себе, который заставляет вас быть очарованным или испуганным.\n\n#### АСТРАЛЬНЫЕ УЧЕНИЯ\n\n**Умение монаха 13-го уровня**\n\nВ качестве действия вы можете потратить 2 очка техник, чтобы стать владеющим одним языком, навыком, инструментом или оружием по вашему выбору, пока вы не выведены из строя или не используете эту особенность снова.\n\n#### АЛМАЗНАЯ ДУША\n\n**Умение монаха 14-го уровня**\n\nВаше владение энергией дарует вам владение всеми спасениями. Кроме того, когда вы совершаете спасение и проваливаете его, вы можете потратить 1 очко техники, чтобы перебросить его. Вы должны взять второй результат.\n\n#### БЕЗВРЕМЕННОЕ \"Я\"\n\n**Умение монаха 17-го уровня**\n\nВаш дух поддерживает вас, тело и разум. Вы получаете следующие преимущества:\n\n* Вы не можете быть магически состарены и не страдаете от немощи старости. Однако вы всё ещё можете умереть от старости.\n* Вам больше не нужны пища или вода.\n* Ваши значения характеристик и максимальное количество хитов не могут быть понижены или уменьшены никакими средствами, кроме заклинания \"желание\".\n\n#### ПУСТОЕ ТЕЛО\n\n**Умение монаха 18-го уровня**\n\nВы можете использовать своё действие, чтобы потратить 4 очка техник, чтобы стать невидимым на 1 минуту. В течение этого времени у вас также есть сопротивление всему урону, кроме урона от силы. Кроме того, вы можете потратить 8 очков техник, чтобы использовать заклинание \"астральная проекция\" в качестве действия (игнорируя стандартное время использования), не нуждаясь в материальных компонентах. Когда вы это делаете, вы не можете брать с собой никаких других существ.\n\n#### ЭПИЧЕСКОЕ БЛАГОСЛОВЕНИЕ\n\n**Умение монаха 20-го уровня**\n\nВаша приверженность пути монаха дарует вам мощную новую способность. Вы получаете следующее эпическое благословение:\n\n* **Безграничная Техника.** Когда вы бросаете инициативу, вы восстанавливаете до 4 израсходованных очков техник. Если вы начинаете свой ход, не имея оставшихся очков техник, вы восстанавливаете 2 очка техник.\n\n### ПОДКЛАСС: ОТКРЫТАЯ РУКА\n\nМонахи Открытой Руки оттачивают своё тело до физического совершенства. Они изучают техники, чтобы толкать и спотыкать своих противников, практикуют продвинутую медитацию, чтобы защитить их от вреда, и разрабатывают секретные техники, чтобы превратить свои тела в высшее оружие.\n\n#### ПРОГРЕССИЯ ОТКРЫТОЙ РУКИ\n\n| УРОВЕНЬ МОНАХА | УМЕНИЯ |\n|---|---|\n| 3-й | Сосредоточенное намерение, Техника открытой руки |\n| 7-й | Целостность тела |\n| 11-й | Спокойная душа |\n| 15-й | Дрожащая ладонь |\n\n#### СОСРЕДОТОЧЕННОЕ НАМЕРЕНИЕ\n\n**Умение Открытой Руки 3-го уровня**\n\nКогда вы или существо в пределах 5 футов от вас совершает проверку характеристики или бросок атаки, вы можете использовать свою реакцию, чтобы бросить свою кость боевых искусств. Цель получает бонус или штраф (по вашему выбору) к своему броску, равный выпавшему числу.\n\nВы можете использовать эту особенность количество раз, равное вашему модификатору МДР. Вы восстанавливаете все израсходованные использования, когда заканчиваете продолжительный отдых.\n\n#### ТЕХНИКА ОТКРЫТОЙ РУКИ\n\n**Умение Открытой Руки 3-го уровня**\n\nВы можете манипулировать энергией своего врага своей собственной. Когда вы попадаете в существо одной из атак, предоставленных вашей техникой \"Шквал ударов\", вы можете наложить один из следующих эффектов на эту цель:\n\n* Она не может использовать реакции до конца вашего следующего хода.\n* Она должна преуспеть в спасении ЛОВ или упасть ничком.\n* Она должна преуспеть в спасении СИЛ или быть оттолкнутой на расстояние до 15 футов от вас.\n\n#### ЦЕЛОСТНОСТЬ ТЕЛА\n\n**Умение Открытой Руки 7-го уровня**\n\nКогда вы бросаете инициативу и у вас есть хотя бы 1 хит, вы восстанавливаете количество хитов, равное вашему модификатору ТЕЛ + вашему уровню монаха.\n\n#### СПОКОЙНАЯ ДУША\n\n**Умение Открытой Руки 11-го уровня**\n\nВы познали путь войны, чтобы лучше ходить по миру в мире. В качестве действия вы можете потратить 3 очка техник, чтобы использовать заклинание \"святилище\" на себе. Заклинание длится до конца вашего следующего короткого или продолжительного отдыха (или его можно закончить раньше как обычно).\n\n#### ДРОЖАЩАЯ ЛАДОНЬ\n\n**Умение Открытой Руки 15-го уровня**\n\nВ качестве действия вы можете совершить одиночный безоружный удар против существа. При попадании вы можете потратить 4 очка техник, чтобы наполнить это существо потенциально смертельными вибрациями, которые длятся количество дней, равное вашему уровню монаха.\n\nВ течение этого времени, пока вы и цель находитесь на одной плоскости, вы можете использовать действие, чтобы прекратить вибрации, разрывая существо на части. Когда вы это делаете, цель должна совершить спасение ТЕЛ. При провале цель получает урон от силы, равный 5 × ваш уровень монаха, и парализована до конца вашего следующего хода. При успехе цель оглушена на 1 минуту, и в конце каждого из их ходов, и каждый раз, когда они получают урон, цель может повторить спасение, прекращая эффект при успехе. Цель, которая проваливает спасение на 5 или более, мгновенно умирает.\n\nКаждый раз, когда вы используете эту особенность после первого, стоимость техники для её использования увеличивается на 2. Когда вы заканчиваете продолжительный отдых, стоимость сбрасывается. Эта особенность может воздействовать только на одну цель за раз.",
  "hitDie": "d8",
  "savingThrows": [
    "СИЛ",
    "ЛОВ"
  ],
  "proficiencies": {
    "skills": {
      "granted": [],
      "choose": 2,
      "from": [
        "Акробатика",
        "Атлетика",
        "История",
        "Проницательность",
        "Религия",
        "Скрытность"
      ]
    },
    "armor": [
      "Нет"
    ],
    "weapons": [
      "Простое оружие",
      "короткие мечи"
    ],
    "tools": [
      "Один на ваш выбор"
    ]
  },
  "startingEquipment": {
    "items": [
      "(a) любое простое оружие.",
      "(a) набор исследователя подземелий или (b) набор исследователя.",
      "(a) 10 дротиков или (b) праща."
    ]
  },
  "levels": [
    {
      "level": 1,
      "proficiencyBonus": "+2",
      "features": [
        "Боевые искусства",
        "Защита без доспехов"
      ]
    },
    {
      "level": 2,
      "proficiencyBonus": "+2",
      "features": [
        "Техники",
        "Движение без доспехов"
      ]
    },
    {
      "level": 3,
      "proficiencyBonus": "+2",
      "features": [
        "Подкласс Монаха"
      ]
    },
    {
      "level": 4,
      "proficiencyBonus": "+2",
      "features": [
        "Улучшение"
      ]
    },
    {
      "level": 5,
      "proficiencyBonus": "+3",
      "features": [
        "Мультиатака (2/Действие Атаки)",
        "Оглушающий удар"
      ]
    },
    {
      "level": 6,
      "proficiencyBonus": "+3",
      "features": [
        "Усиленные удары",
        "Уклонение"
      ]
    },
    {
      "level": 7,
      "proficiencyBonus": "+3",
      "features": [
        "Особенность Подкласса"
      ]
    },
    {
      "level": 8,
      "proficiencyBonus": "+3",
      "features": [
        "Улучшение"
      ]
    },
    {
      "level": 9,
      "proficiencyBonus": "+4",
      "features": [
        "Совершенное движение"
      ]
    },
    {
      "level": 10,
      "proficiencyBonus": "+4",
      "features": [
        "Героический дар"
      ]
    },
    {
      "level": 11,
      "proficiencyBonus": "+4",
      "features": [
        "Особенность Подкласса"
      ]
    },
    {
      "level": 12,
      "proficiencyBonus": "+4",
      "features": [
        "Улучшение"
      ]
    },
    {
      "level": 13,
      "proficiencyBonus": "+5",
      "features": [
        "Астральные учения"
      ]
    },
    {
      "level": 14,
      "proficiencyBonus": "+5",
      "features": [
        "Алмазная душа"
      ]
    },
    {
      "level": 15,
      "proficiencyBonus": "+5",
      "features": [
        "Особенность Подкласса"
      ]
    },
    {
      "level": 16,
      "proficiencyBonus": "+5",
      "features": [
        "Улучшение"
      ]
    },
    {
      "level": 17,
      "proficiencyBonus": "+6",
      "features": [
        "Безвременное \"я\""
      ]
    },
    {
      "level": 18,
      "proficiencyBonus": "+6",
      "features": [
        "Пустое тело"
      ]
    },
    {
      "level": 19,
      "proficiencyBonus": "+6",
      "features": [
        "Улучшение"
      ]
    },
    {
      "level": 20,
      "proficiencyBonus": "+6",
      "features": [
        "Эпический дар"
      ]
    }
  ],
  "features": [],
  "subclasses": [],
  "type": "class",
  "id": "BFRD:class/monah",
  "slug": "monah",
  "name": "МОНАХ",
  "schemaVersion": "1.0.0",
  "src": {
    "abbr": "BFRD",
    "name": "Black Flag Reference Document",
    "version": "1.0",
    "url": "https://bfrd.net/",
    "license": "Open RPG Creative License (ORC)",
    "hash": "42f472229bc21e0fb2da3e9e8d42b89049098bdc5d0e12c216daa4f80fb51b60"
  },
  "summary": "Как монах, вы обладаете следующими особенностями класса.",
  "sourceFile": "input/classes/monk.md"
}