{
  "description": "### КЛАССОВЫЕ УМЕНИЯ\n\nКак плут, вы обладаете следующими особенностями класса.\n\n#### ХИТЫ\n\n* **Кость хитов:** 1к8 за каждый уровень плута\n* **Хиты на 1-м уровне:** 8 + ваш модификатор ТЕЛ\n* **Хиты на более высоких уровнях:** 1к8 (или 5) + ваш модификатор ТЕЛ за каждый уровень плута после 1-го\n\n#### ВЛАДЕНИЯ\n\n* **Доспехи:** Легкие доспехи\n* **Оружие:** Простое оружие, воинское оружие со свойством \"Фехтовальное\"\n* **Инструменты:** Воровские инструменты\n* **Спасброски:** ЛОВ, ИНТ\n* **Навыки:** Выберите четыре из следующих: Акробатика, Атлетика, Обман, Проницательность, Запугивание, Расследование, Восприятие, Выступление, Убеждение, Ловкость Рук и Скрытность\n\n#### ПРОГРЕССИЯ ПЛУТА\n\n| УРОВЕНЬ | БМ | СКРЫТАЯ АТАКА | УМЕНИЯ |\n|---|---|---|---|\n| 1-й | +2 | 1d6 | Компетентность (2), Скрытая атака, Воровской жаргон |\n| 2-й | +2 | 1d6 | Хитрое действие |\n| 3-й | +2 | 2d6 | Подкласс Плута |\n| 4-й | +2 | 2d6 | Улучшение |\n| 5-й | +3 | 3d6 | Невероятное уклонение |\n| 6-й | +3 | 3d6 | Увёртливость, Компетентность (4) |\n| 7-й | +3 | 4d6 | Умение подкласса |\n| 8-й | +3 | 4d6 | Улучшение |\n| 9-й | +4 | 5d6 | Надёжный талант |\n| 10-й | +4 | 5d6 | Героический дар |\n| 11-й | +4 | 6d6 | Умение подкласса |\n| 12-й | +4 | 6d6 | Улучшение |\n| 13-й | +5 | 7d6 | Точный критический удар (1 кость) |\n| 14-й | +5 | 7d6 | Обострённые чувства |\n| 15-й | +5 | 8d6 | Умение подкласса |\n| 16-й | +5 | 8d6 | Улучшение |\n| 17-й | +6 | 9d6 | Точный критический удар (2 кости) |\n| 18-й | +6 | 9d6 | Неуловимость |\n| 19-й | +6 | 10d6 | Улучшение |\n| 20-й | +6 | 10d6 | Эпический дар |\n\n#### НАЧАЛЬНОЕ СНАРЯЖЕНИЕ\n\n* (а) рапира или (б) короткий меч\n* (а) короткий лук и колчан с 20 стрелами или (б) короткий меч\n* (а) набор взломщика, (б) набор исследователя подземелий или (в) набор путешественника\n* Кожаный доспех, два кинжала и набор воровских инструментов\n\n### КОМПЕТЕНТНОСТЬ\n\n**Умение Плута 1-го и 6-го уровней**\n\nВыберите два ваших владения навыками, или одно владение навыком и одно владение инструментом. Удвойте ваш БМ для любой проверки характеристики, которую вы совершаете, используя одно из выбранных владений.\nНа 6-м уровне выберите еще два ваших владения (любая комбинация навыков или инструментов), чтобы получить это преимущество.\n\n### СКРЫТАЯ АТАКА\n\n**Умение Плута 1-го уровня**\n\nВы знаете, как наносить удары незаметно и использовать замешательство врага. Один раз в ход вы можете нанести дополнительный урон 1к6 одному существу, по которому вы попали атакой, если у вас есть преимущество на бросок атаки. Оружие, которое вы используете, должно иметь свойство \"Фехтовальное\" или быть дальнобойным оружием.\nВам не нужно преимущество на бросок атаки, если другой враг цели находится в пределах 5 футов от нее, этот враг не недееспособен, и у вас нет помехи на бросок атаки.\nКоличество дополнительного урона, который вы наносите, увеличивается по мере получения уровней в этом классе, как показано в колонке \"Скрытая Атака\" таблицы Прогрессии Плута.\n\n*(Примечание: Таблица Прогрессии Плута отсутствует в предоставленном тексте, но упоминается здесь.)*\n\n### ВОРОВСКОЙ ЖАРГОН\n\n**Умение Плута 1-го уровня**\n\nВо время вашего обучения плутовскому ремеслу вы изучили Воровской Жаргон — тайную смесь диалекта, жаргона и кода, которая позволяет вам скрывать сообщения в кажущемся нормальным разговоре. Только другое существо, знающее Воровской Жаргон, понимает такие сообщения. Передача сообщения на Воровском Жаргоне занимает в четыре раза больше времени, чем изложение той же мысли обычным языком.\nКроме того, вы понимаете набор тайных знаков и символов, используемых для передачи коротких, простых сообщений, таких как информация об опасности в области или о территории гильдии воров, о наличии поблизости добычи, или о том, являются ли люди в области легкой добычей или предоставят убежище для воров в бегах.\n\n### ХИТРОЕ ДЕЙСТВИЕ\n\n**Умение Плута 2-го уровня**\n\nВаше быстрое мышление и ловкость позволяют вам быстро двигаться и действовать. Вы можете использовать бонусное действие, чтобы совершить действие Рывок, Отход или Засада.\n\n#### УМЕНИЯ ПОДКЛАССА ПЛУТА\n\n**Умение Плута 3-го, 7-го, 11-го и 15-го уровней**\n\nВыберите подкласс, представляющий ваш специализированный набор навыков, либо Вышибала, либо Вор (подробно описаны в конце этого класса). Ваш выбор дает вам умения на 3-м, 7-м, 11-м и 15-м уровне.\n\n*(Примечание: Подкласс Вышибала не представлен в предоставленном тексте.)*\n\n### УЛУЧШЕНИЕ\n\n**Умение Плута 4-го, 8-го, 12-го, 16-го и 19-го уровней**\n\nВыберите одно из следующих улучшений (значения характеристик не могут быть подняты выше 20 с помощью этого умения):\n\n*   Увеличьте одно значение характеристики на 2.\n*   Увеличьте два разных значения характеристик на 1 каждое.\n*   Увеличьте одно значение характеристики на 1 и выберите талант из списка технических талантов.\n\n### НЕВЕРОЯТНОЕ УКЛОНЕНИЕ\n\n**Умение Плута 5-го уровня**\n\nКогда атакующий, которого вы можете видеть, попадает по вам атакой, вы можете использовать свою реакцию, чтобы уменьшить урон атаки против вас вдвое.\n\n### УВЁРТЛИВОСТЬ\n\n**Умение Плута 6-го уровня**\n\nВы можете увернуться от некоторых эффектов по области, таких как дыхание молнией синего дракона или заклинание *\"Огненный шар\"*. Когда вы подвергаетесь эффекту, который позволяет вам совершить спасбросок ЛОВ, чтобы получить только половину урона, вы вместо этого не получаете урона, если преуспели в спасброске, и только половину урона, если провалили.\n\n### НАДЁЖНЫЙ ТАЛАНТ\n\n**Умение Плута 9-го уровня**\n\nВы отточили выбранные навыки почти до совершенства. Когда вы совершаете проверку характеристики с использованием навыка, считайте результат броска к20, равный 9 или ниже, как если бы вы выбросили 10.\n\n### ГЕРОИЧЕСКИЙ ДАР\n\n**Умение Плута 10-го уровня**\n\nВаша приверженность пути плута дает вам новую мощную способность. Выберите один из следующих героических даров:\n\n*   **Мастер Побега.** Когда вы подвергаетесь эффекту, который позволяет вам совершить любой вид спасброска (включая спасброски ЛОВ), чтобы получить только половину урона, вы вместо этого не получаете урона, если преуспели в спасброске, и только половину урона, если провалили.\n*   **Мастер на все руки.** Когда вы получаете новый талант, вы можете выбрать его из любого списка талантов. Немедленно получите один талант по вашему выбору (для которого вы соответствуете требованиям), когда получаете это умение.\n\n### ТОЧНЫЙ КРИТ\n\n**Умение Плута 13-го и 17-го уровней**\n\nВы совершаете критическое попадание при результате броска к20, равном 19 или 20, с дальнобойным оружием и оружием со свойством \"Фехтовальное\". Кроме того, вы можете бросить одну дополнительную кость урона оружия (не дополнительную кость Скрытой Атаки) при определении дополнительного урона от критического попадания атакой дальнобойным оружием или атакой, совершенной Фехтовальным оружием.\nЭтот дополнительный урон увеличивается до двух дополнительных костей на 17-м уровне.\n\n### ОСТРОЕ ЧУТЬЕ\n\n**Умение Плута 14-го уровня**\n\nВы обладаете острым чутьем в радиусе 10 футов. Ваше острое чутье перестает функционировать, пока вы оглушены или иным образом лишены слуха.\n\n### НЕУЛОВИМОСТЬ\n\n**Умение Плута 18-го уровня**\n\nВы настолько неуловимы, что атакующие редко получают над вами преимущество. Пока вы не недееспособны, броски атаки не могут иметь преимущество против вас, независимо от источника преимущества.\n\n### ЭПИЧЕСКИЙ ДАР\n\n**Умение Плута 20-го уровня**\n\nВаша приверженность пути плута дает вам новую мощную способность. Вы получаете следующий эпический дар:\n\n*   **Удар Удачи.** У вас получается, когда это важно. Если ваша атака промахивается по цели в пределах нормальной дистанции, вы можете превратить промах в попадание. В качестве альтернативы, если вы проваливаете проверку характеристики, вы можете считать результат броска к20 равным 20. После использования этого умения вы не можете использовать его снова, пока не закончите короткий или продолжительный отдых.\n\n#### ПОДКЛАСС: ВОР\n\nУ вас репутация человека с быстрым умом и еще более быстрыми пальцами. Оставьте перерезание глоток и мошенничество менее значимым негодяям. Вы живете, чтобы освобождать сокровища, хранящиеся под замком. Острые ощущения от обхода запечатанной двери, сложной ловушки или другого \"непреодолимого\" препятствия — вот настоящая награда, за которой следует плата, полученная за то, что вы взяли.\n\n#### ПРОГРЕССИЯ ВОРА\n\n| УРОВЕНЬ ПЛУТА | УМЕНИЯ                  |\n| :-----------: | :---------------------- |\n| 3-й           | Быстрые Руки, Верхолаз |\n| 7-й           | Оценивающий Взгляд      |\n| 11-й          | Специалист по Ловушкам |\n| 15-й          | Воровские Рефлексы      |\n\n#### БЫСТРЫЕ РУКИ\n\n**Умение Вора 3-го уровня**\n\nОпыт отточил ваши навыки, позволяя вам выполнять точную работу мгновенно. В дополнение к стандартным использованиям, теперь вы можете использовать бонусное действие, предоставляемое вашим умением Хитрое Действие, чтобы сделать любое из следующего:\n\n*   Совершить проверку ЛОВ (Ловкость Рук).\n*   Совершить действие Использовать Предмет.\n*   Использовать воровские инструменты для попытки обезвредить ловушку или открыть замок.\n\n#### ВЕРХОЛАЗ\n\n**Умение Вора 3-го уровня**\n\nВы никогда не встречали стену, которую не могли бы покорить, и лазание по ним для вас — вторая натура. Вы получаете скорость лазания, равную вашей скорости ходьбы. Если у вас уже есть скорость лазания, когда вы получаете это умение, она увеличивается на 10 футов.\nКроме того, когда вы совершаете прыжок в длину, вы преодолеваете количество футов, равное вашей скорости ходьбы, если вы двигались пешком не менее 10 футов непосредственно перед прыжком. Когда вы совершаете прыжок в длину с места, вы можете прыгнуть на половину вашей скорости ходьбы. В любом случае, каждый фут, который вы преодолеваете в прыжке, стоит фута движения. В случае, если для преодоления или увеличения дистанции прыжка требуется проверка СИЛ (Атлетика), вы можете вместо этого выбрать проверку ЛОВ (Акробатика).\n\n#### ОЦЕНИВАЮЩИЙ ВЗГЛЯД\n\n**Умение Вора 7-го уровня**\n\nВы развили глаз на качество. Действием вы можете осмотреть любой предмет в пределах 10 футов от вас, который вы можете видеть, чтобы узнать, является ли он немагическим или магическим. Если предмет немагический, вы немедленно узнаете его приблизительную стоимость в золотых монетах. Вы также узнаете, является ли предмет подделкой или может ли он скрывать другие предметы внутри себя (хотя вы не узнаете, скрывает ли он в данный момент предметы или какие это предметы).\nЕсли предмет магический, вы можете потратить 1 минуту на его изучение, чтобы узнать его тип, редкость, проклят ли он, и требует ли он настройки (и любые специфические требования к настройке, которые у него есть). После того как вы изучили магический предмет таким образом, вы узнаете, как его использовать, и можете игнорировать любые требования к классу или умению, которые обычно мешали бы вам его использовать (хотя вы все равно должны соблюдать любые ограничения по уровню). Если магический предмет требует использования базовой характеристики заклинаний, используйте вашу ЛОВ для определения СЛ спасброска от заклинания или бонуса атаки заклинанием.\n\n#### СПЕЦИАЛИСТ ПО ЛОВУШКАМ\n\n**Умение Вора 11-го уровня**\n\nКогда вы или существо в пределах 5 футов от вас активируете ловушку, вы можете использовать свою реакцию, чтобы бросить проверку характеристики для попытки обезвредить ловушку. Если вы преуспели, ловушка обезврежена и не активируется. Если вы потерпели неудачу, ловушка активируется как обычно.\nКроме того, теперь вы можете обезвреживать любые магические ловушки, которые обычно требуют использования заклинания *\"Рассеивание магии\"*. Когда вы это делаете, совершите проверку характеристики, используя только ваш модификатор ЛОВ, не добавляя никаких других модификаторов к броску. Если результат равен или превышает СЛ ловушки (ваш Мастер знает это число), она обезвреживается, как если бы вы успешно применили заклинание *\"Рассеивание магии\"*.\n\n#### ВОРОВСКИЕ РЕФЛЕКСЫ\n\n**Умение Вора 15-го уровня**\n\nВы стали искусны в устройстве засад и быстром избегании опасности. Теперь вы можете совершать два хода в течение первого раунда любого боя. Вы совершаете свой первый ход по вашей обычной инициативе и ваш второй ход по вашей инициативе минус 10. Вы не можете использовать это умение, если вы застигнуты врасплох.",
  "hitDie": "d8",
  "savingThrows": [
    "ЛОВ",
    "ИНТ"
  ],
  "proficiencies": {
    "skills": {
      "granted": [],
      "choose": 4,
      "from": [
        "Акробатика",
        "Атлетика",
        "Обман",
        "Проницательность",
        "Запугивание",
        "Расследование",
        "Восприятие",
        "Выступление",
        "Убеждение",
        "Ловкость Рук",
        "Скрытность"
      ]
    },
    "armor": [
      "Легкие доспехи"
    ],
    "weapons": [
      "Простое оружие",
      "воинское оружие со свойством \"Фехтовальное\""
    ],
    "tools": [
      "Воровские инструменты"
    ]
  },
  "startingEquipment": {
    "items": [
      "(а) рапира или (б) короткий меч",
      "(а) короткий лук и колчан с 20 стрелами или (б) короткий меч",
      "(а) набор взломщика, (б) набор исследователя подземелий или (в) набор путешественника",
      "Кожаный доспех, два кинжала и набор воровских инструментов"
    ]
  },
  "levels": [
    {
      "level": 1,
      "proficiencyBonus": "+2",
      "features": [
        "Компетентность (2)",
        "Скрытая атака",
        "Воровской жаргон"
      ]
    },
    {
      "level": 2,
      "proficiencyBonus": "+2",
      "features": [
        "Хитрое действие"
      ]
    },
    {
      "level": 3,
      "proficiencyBonus": "+2",
      "features": [
        "Подкласс Плута"
      ]
    },
    {
      "level": 4,
      "proficiencyBonus": "+2",
      "features": [
        "Улучшение"
      ]
    },
    {
      "level": 5,
      "proficiencyBonus": "+3",
      "features": [
        "Невероятное уклонение"
      ]
    },
    {
      "level": 6,
      "proficiencyBonus": "+3",
      "features": [
        "Увёртливость",
        "Компетентность (4)"
      ]
    },
    {
      "level": 7,
      "proficiencyBonus": "+3",
      "features": [
        "Умение подкласса"
      ]
    },
    {
      "level": 8,
      "proficiencyBonus": "+3",
      "features": [
        "Улучшение"
      ]
    },
    {
      "level": 9,
      "proficiencyBonus": "+4",
      "features": [
        "Надёжный талант"
      ]
    },
    {
      "level": 10,
      "proficiencyBonus": "+4",
      "features": [
        "Героический дар"
      ]
    },
    {
      "level": 11,
      "proficiencyBonus": "+4",
      "features": [
        "Умение подкласса"
      ]
    },
    {
      "level": 12,
      "proficiencyBonus": "+4",
      "features": [
        "Улучшение"
      ]
    },
    {
      "level": 13,
      "proficiencyBonus": "+5",
      "features": [
        "Точный критический удар (1 кость)"
      ]
    },
    {
      "level": 14,
      "proficiencyBonus": "+5",
      "features": [
        "Обострённые чувства"
      ]
    },
    {
      "level": 15,
      "proficiencyBonus": "+5",
      "features": [
        "Умение подкласса"
      ]
    },
    {
      "level": 16,
      "proficiencyBonus": "+5",
      "features": [
        "Улучшение"
      ]
    },
    {
      "level": 17,
      "proficiencyBonus": "+6",
      "features": [
        "Точный критический удар (2 кости)"
      ]
    },
    {
      "level": 18,
      "proficiencyBonus": "+6",
      "features": [
        "Неуловимость"
      ]
    },
    {
      "level": 19,
      "proficiencyBonus": "+6",
      "features": [
        "Улучшение"
      ]
    },
    {
      "level": 20,
      "proficiencyBonus": "+6",
      "features": [
        "Эпический дар"
      ]
    }
  ],
  "features": [],
  "subclasses": [],
  "type": "class",
  "id": "BFRD:class/plut",
  "slug": "plut",
  "name": "ПЛУТ",
  "schemaVersion": "1.0.0",
  "src": {
    "abbr": "BFRD",
    "name": "Black Flag Reference Document",
    "version": "1.0",
    "url": "https://bfrd.net/",
    "license": "Open RPG Creative License (ORC)",
    "hash": "154f8265251752d691a63ba8f6240619ac6afb353bfe75198b6afc8331123ff6"
  },
  "summary": "Как плут, вы обладаете следующими особенностями класса.",
  "sourceFile": "input/classes/rogue.md"
}