{
  "description": "### КЛАССОВЫЕ УМЕНИЯ\n\nКак следопыт, вы обладаете следующими особенностями класса.\n\n#### ХИТЫ\n\n* **Кость хитов:** 1к10 за каждый уровень следопыта\n* **Хиты на 1-м уровне:** 10 + ваш модификатор ТЕЛ\n* **Хиты на более высоких уровнях:** 1к10 (или 6) + ваш модификатор ТЕЛ за каждый уровень следопыта после 1-го\n\n#### ВЛАДЕНИЯ\n\n* **Доспехи:** Легкие доспехи, средние доспехи и щиты\n* **Оружие:** Простое оружие, воинское оружие\n* **Инструменты:** На ваш выбор набор травника, инструменты навигатора или инструменты ловушечника\n* **Спасброски:** СИЛ, ЛОВ\n* **Навыки:** Выберите три из следующих: Уход за животными, Атлетика, Проницательность, Расследование, Природа, Восприятие, Скрытность и Выживание\n\n#### НАЧАЛЬНОЕ СНАРЯЖЕНИЕ\n\n* (а) чешуйчатый доспех или (б) кожаный доспех\n* (а) два коротких меча или (б) два простых оружия\n* (а) набор исследователя подземелий или (б) набор путешественника\n* Длинный лук и колчан с 20 стрелами\n\n#### ПРОГРЕССИЯ СЛЕДОПЫТА\n\n| УРОВЕНЬ | БМ | УМЕНИЯ | ИЗВЕСТНЫЕ ЗАКЛИНАНИЯ | 1-й | 2-й | 3-й | 4-й | 5-й |\n| :------: | :-: | :----------------------------------- | :------------------- | :-: | :-: | :-: | :-: | :-: | :--: |\n| 1-й     | +2  | Исследователь, Мистическая Метка   | -                    | -   | -   | -   | -   | - |\n| 2-й     | +2  | Воинское Действие, Использование Заклинаний | 2                    | 2   | -   | -   | -   | - |\n| 3-й     | +2  | Подкласс Следопыта                   | 3                    | 3   | -   | -   | -   | - |\n| 4-й     | +2  | Улучшение                            | 3                    | 3   | -   | -   | -   | - |\n| 5-й     | +3  | Мультиатака (2/Действие Атаки)       | 4                    | 4   | 2   | -   | -   | - |\n| 6-й     | +3  | Усиленная Метка, Мистическая Метка (к6) | 4                    | 4   | 2   | -   | -   | - |\n| 7-й     | +3  | Умение Подкласса                     | 5                    | 4   | 3   | -   | -   | - |\n| 8-й     | +3  | Улучшение                            | 5                    | 4   | 3   | -   | -   | - |\n| 9-й     | +4  | Шаг Преследователя                   | 6                    | 4   | 3   | 2   | -   | - |\n| 10-й    | +4  | Героический Дар                      | 6                    | 4   | 3   | 2   | -   | - |\n| 11-й    | +4  | Умение Подкласса                     | 7                    | 4   | 3   | 3   | -   | - |\n| 12-й    | +4  | Улучшение                            | 7                    | 4   | 3   | 3   | -   | - |\n| 13-й    | +5  | Мистическая Метка (к8)              | 8                    | 4   | 3   | 3   | 1   | - |\n| 14-й    | +5  | Острое Чутье                         | 8                    | 4   | 3   | 3   | 1   | - |\n| 15-й    | +5  | Умение Подкласса                     | 9                    | 4   | 3   | 3   | 2   | - |\n| 16-й    | +5  | Улучшение                            | 9                    | 4   | 3   | 3   | 2   | - |\n| 17-й    | +6  | Мистическая Метка (к10)             | 10                   | 4   | 3   | 3   | 3   | 1 |\n| 18-й    | +6  | Странник                             | 10                   | 4   | 3   | 3   | 3   | 1 |\n| 19-й    | +6  | Улучшение                            | 11                   | 4   | 3   | 3   | 3   | 2 |\n| 20-й    | +6  | Эпический Дар                        | 11                   | 4   | 3   | 3   | 3   | 2 |\n\n### ИССЛЕДОВАТЕЛЬ\n\n**Умение Следопыта 1-го уровня**\n\nВаша способность справляться с трудностями окружающей среды непревзойденна. Вы получаете следующие преимущества:\n\n* Вы получаете либо скорость лазания, либо скорость плавания, равную вашей базовой скорости передвижения.\n* Вы совершаете с преимуществом проверки для выслеживания существа.\n* Ваша скорость не уменьшается вдвое при движении по немагической или магической труднопроходимой местности. Вы по-прежнему страдаете от других штрафов, вызванных движением по труднопроходимой местности, как обычно.\n\n### МИСТИЧЕСКАЯ МЕТКА\n\n**Умение Следопыта 1-го, 6-го, 13-го и 17-го уровней**\n\nКогда вы попадаете по существу броском атаки, вы можете мистически пометить его как свою избранную добычу. Существо остается помеченным в течение 1 минуты, пока вы не используете это умение, чтобы пометить другое существо, или пока не станете недееспособным.\n\nПока существо помечено (включая атаку, которая вызвала метку), вы наносите ему дополнительный урон 1к4 (того же типа, что и урон оружия) каждый раз, когда успешно попадаете по нему атакой оружием.\nВы можете использовать это умение количество раз, равное вашему БМ. Вы восстанавливаете все использования, когда заканчиваете продолжительный отдых.\nЭтот дополнительный урон увеличивается по мере получения уровней следопыта, становясь 1к6 на 6-м уровне, 1к8 на 13-м и 1к10 на 17-м.\n\n### ВОИНСКОЕ ДЕЙСТВИЕ\n\n**Умение Следопыта 2-го уровня**\n\nВаш тактический опыт позволяет вам быстро действовать на поле боя. Вы можете совершать бонусное действие в каждый свой ход в бою, чтобы использовать опцию оружия или одно из воинских действий, предоставляемых этим умением.\nВыберите одно из следующих воинских действий, которые вы знаете.\n\n#### Прицеливание\n\n**Требуется владение Дальнобойным или Метательным оружием**\n\nБонусным действием вы тратите время, чтобы повысить эффективность вашей следующей атаки дальнобойным оружием. Выберите одну цель, которую вы можете видеть. Если вы совершаете атаку дальнобойным оружием по этой цели до конца вашего хода, удвойте свой БМ для первого броска атаки.\n\n#### Быстрый Удар\n\n**Требуется владение Двумя Легкими Оружиями**\n\nПосле того как вы совершаете действие Атаки в свой ход и атакуете Легким рукопашным оружием, которое держите в одной руке, вы можете использовать бонусное действие, чтобы совершить две атаки другим Легким рукопашным оружием, которое держите в другой руке — вместо одной атаки, обычно предоставляемой боем двумя оружиями. Не добавляйте модификатор характеристики к урону этих дополнительных атак, если только модификатор не отрицательный.\n\n### ИСПОЛЬЗОВАНИЕ ЗАКЛИНАНИЙ\n\n**Умение Следопыта 2-го уровня**\n\nНа 2-м уровне вы усиливаете свое воинское мастерство способностью использовать Первородные заклинания.\n\n#### Использование заклинаний\n\nВы знаете небольшое количество заклинаний и можете использовать любое из них, используя ячейку Первородного заклинания круга заклинания или выше. Вам не нужно подготавливать заклинания заранее.\nТаблица Прогрессии Следопыта показывает, сколько заклинаний вы знаете и сколько у вас есть ячеек Первородных заклинаний на данном уровне. Например, на 5-м уровне у вас есть четыре ячейки 1-го круга и две ячейки 2-го круга. Если вы знаете заклинание 1-го круга *\"Дружба с животными\"* и у вас есть доступные ячейки 1-го и 2-го кругов, вы можете использовать *\"Дружба с животными\"*, используя любую из ячеек. Если вы используете ячейку 1-го круга, у вас останется три ячейки 1-го круга.\nВы восстанавливаете все использованные ячейки заклинаний, когда заканчиваете продолжительный отдых.\n\n#### Известные заклинания 1-го круга и выше\n\nНа 2-м уровне выберите два заклинания 1-го круга из списка Первородных заклинаний, которые вы знаете.\nКолонка \"Известные Заклинания\" таблицы Прогрессии Следопыта показывает, когда вы изучаете дополнительные Первородные заклинания. Каждое выбранное вами заклинание должно быть из круга, для которого у вас есть ячейки Первородных заклинаний. Например, когда вы достигаете 5-го уровня следопыта, вы можете изучить одно новое Первородное заклинание 1-го или 2-го круга.\nКроме того, когда вы получаете уровень следопыта, вы можете выбрать одно Первородное заклинание, которое вы знаете, и заменить его другим заклинанием по вашему выбору из списка Первородных заклинаний. Заменяющее заклинание должно быть круга, для которого у вас есть ячейки Первородных заклинаний.\n\n#### Базовая характеристика заклинаний\n\nМудрость (МДР) является вашей базовой характеристикой для заклинаний. Ваш модификатор МДР определяет СЛ спасброска или модификатор атаки для некоторых заклинаний, которые вы используете:\n\nСЛ спасброска от заклинания = 8 + ваш бонус мастерства (БМ) + ваш модификатор МДР\nМодификатор атаки заклинанием = ваш бонус мастерства (БМ) + ваш модификатор МДР\n\n#### Заклинательная фокусировка\n\nВы можете использовать друидическую фокусировку в качестве заклинательной фокусировки для ваших Первородных заклинаний.\n\n#### УМЕНИЯ ПОДКЛАССА СЛЕДОПЫТА\n\n**Умение Следопыта 3-го, 7-го, 11-го и 15-го уровней**\n\nВыберите подкласс, отражающий вашу связь с миром природы, либо Охотник, либо Хозяин Стаи (подробно описано в конце этого класса). Ваш выбор дает вам заклинания и другие умения на 3-м, 7-м, 11-м и 15-м уровнях.\n\n#### Заклинания Призвания\n\nУ каждого подкласса следопыта есть список заклинаний призвания, к которым вы получаете доступ, как только можете использовать заклинания этого круга (как показано в таблице Прогрессии Следопыта). Как только вы получаете такое заклинание, оно всегда находится в вашем списке известных заклинаний и не учитывается в общем количестве известных вам заклинаний. Однако использование заклинания призвания все равно расходует ячейку Первородного заклинания как обычно.\nЕсли одно из этих заклинаний не входит в список Первородных заклинаний, оно все равно считается для вас Первородным заклинанием. Вы не можете заменять заклинания призвания при получении уровня следопыта.\n\n### УЛУЧШЕНИЕ\n\n**Умение Следопыта 4-го, 8-го, 12-го, 16-го и 19-го уровней**\n\nВыберите одно из следующих улучшений (значения характеристик не могут быть подняты выше 20 с помощью этого умения):\n\n*   Увеличьте одно значение характеристики на 2.\n*   Увеличьте два разных значения характеристик на 1 каждое.\n*   Увеличьте одно значение характеристики на 1 и выберите талант из списка воинских или технических талантов.\n\n### МУЛЬТИАТАКА\n\n**Умение Следопыта 5-го уровня**\n\nВаша физическая мощь возросла. В свой ход вы можете совершить две атаки, когда совершаете действие Атаки.\n\n### УСИЛЕННАЯ МЕТКА\n\n**Умение Следопыта 6-го уровня**\n\nВаши инстинкты обострились, даруя вам сверхъестественное знание о вашей добыче. Пока существо, помеченное вашим умением Мистическая Метка, находится в пределах 60 футов от вас, вы знаете его точное местоположение, и оно не может получить преимущество на атаки против вас из-за того, что оно невидимо или иным образом скрыто. Кроме того, когда вы атакуете помеченное существо в пределах 60 футов от вас, невозможность видеть его не накладывает помеху на ваши броски атаки против него.\n\n### ШАГ ПРЕСЛЕДОВАТЕЛЯ\n\n**Умение Следопыта 9-го уровня**\n\nПока вы находитесь в тусклом свете, темноте, или слегка или сильно заслонены листвой, туманом или другим природным явлением, вы можете использовать бонусное действие, чтобы магически стать невидимым вместе со всем снаряжением, которое вы носите или несете, до начала вашего следующего хода. Эта невидимость заканчивается раньше, если вы атакуете или используете заклинание.\nВы можете использовать это умение количество раз, равное вашему БМ, и восстанавливаете все использования, когда завершаете продолжительный отдых.\n\n### ГЕРОИЧЕСКИЙ ДАР\n\n**Умение Следопыта 10-го уровня**\n\nВаша приверженность пути следопыта дает вам новую мощную способность. Выберите один из следующих героических даров:\n\n*   **Путь Хищника.** Когда вы бросаете инициативу, вы можете потратить одно использование Мистической Метки, чтобы автоматически пометить одно существо, которое вы видите, атака не требуется. Кроме того, если помеченное существо доведено до 0 ХП, вы можете использовать свою реакцию, чтобы перенести метку на другое существо, которое вы видите в пределах 60 футов от первоначальной цели.\n*   **Путь Мудреца.** Вы изучаете два заговора по вашему выбору из списка Первородных заклинаний. Вы также изучаете два ритуальных заклинания по вашему выбору из списка Первородных заклинаний. Оба ритуальных заклинания должны быть из кругов, для которых у вас есть ячейки заклинаний, как показано в таблице Прогрессии Следопыта. Ритуальные заклинания, изученные таким образом, не учитываются в вашем общем количестве известных заклинаний. МДР является вашей базовой характеристикой для заговоров и ритуальных заклинаний, изученных таким образом. Когда вы получаете уровень следопыта, вы можете заменить один из этих заговоров и один из этих ритуалов другим заговором или ритуальным заклинанием из списка Первородных заклинаний, при условии, что заменяющее ритуальное заклинание все еще относится к кругу, для которого у вас есть ячейки заклинаний.\n\n### ОСТРОЕ ЧУТЬЕ\n\n**Умение Следопыта 14-го уровня**\n\nВы обладаете острым чутьем в радиусе 10 футов. Ваше острое чутье перестает функционировать, пока вы оглушены или иным образом лишены слуха.\n\n### СТРАННИК\n\n**Умение Следопыта 18-го уровня**\n\nВаше передвижение никогда не провоцирует атаки по возможности, и вы имеете преимущество на любую проверку, сделанную для сопротивления эффекту, который мог бы сделать вас схваченным, опутанным или парализованным, или который иным образом уменьшил бы вашу скорость передвижения до 0 футов.\n\n### ЭПИЧЕСКИЙ ДАР\n\n**Умение Следопыта 20-го уровня**\n\nВаша приверженность пути следопыта дает вам новую мощную способность. Вы получаете следующий эпический дар:\n\n*   **Убийца Врагов.** Вы можете добавить свой модификатор МДР либо к броску атаки, либо к броску урона каждой атаки, которую вы совершаете против существа, помеченного вашей Мистической Меткой, в свой ход.\n\n### ПОДКЛАСС: ОХОТНИК\n\nСледопыты, внимающие зову Охотника, — не просто ловушечники или меховщики. Они — последняя линия обороны между миром природы и сверхъестественным. Охотники ищут, выслеживают и убивают чудовищных хищников, таких как потусторонние существа, исчадия и нежить, которые опустошают население своей злой магией.\n\n#### ПРОГРЕССИЯ ОХОТНИКА\n\n| УРОВЕНЬ СЛЕДОПЫТА | УМЕНИЯ                                                          |\n| :---------------: | :--------------------------------------------------------------- |\n| 3-й               | Заклинания Призвания Охотника, Инстинкт Убийцы, Неустанное Преследование |\n| 7-й               | Излюбленный Враг                                                |\n| 11-й              | Нет Спасенья                                                    |\n| 15-й              | Щит Хищника                                                    |\n\n#### ЗАКЛИНАНИЯ ПРИЗВАНИЯ ОХОТНИКА\n\n**Умение Охотника 3-го уровня**\n\nВы получаете заклинания призвания на уровнях следопыта, указанных в таблице Заклинаний Призвания Охотника. Смотрите описание умения Подкласс Следопыта, чтобы узнать, как работают эти заклинания.\n\n**ЗАКЛИНАНИЯ ПРИЗВАНИЯ ОХОТНИКА**\n\n| УРОВЕНЬ СЛЕДОПЫТА | ЗАКЛИНАНИЯ                 |\n| :---------------: | :------------------------- |\n| 3-й               | защита от добра и зла    |\n| 5-й               | туманный шаг               |\n| 9-й               | невидимость                |\n| 13-й              | изгнание                   |\n| 17-й              | великое удержание          |\n\n#### ИНСТИНКТ УБИЙЦЫ\n\n**Умение Охотника 3-го уровня**\n\nБонусным действием выберите существо в пределах 60 футов от вас, которое вы можете видеть. Вы немедленно узнаете иммунитеты, сопротивления и уязвимости существа, или узнаете, если у него их нет. Это умение не работает, если цель магически скрыта заклинанием *\"невидимость\"* или подобным эффектом, противодействующим магии прорицания.\nВы можете использовать это умение количество раз, равное вашему БМ, и восстанавливаете все его использования, когда заканчиваете продолжительный отдых.\n\n#### НЕУСТАННОЕ ПРЕСЛЕДОВАНИЕ\n\n**Умение Охотника 3-го уровня**\n\nВаша настойчивость изматывает даже могущественных врагов. Когда вы попадаете по существу атакой оружием, вы наносите дополнительный урон, если хиты цели ниже максимума. Дополнительный урон равен количеству, которое наносит ваше умение Мистическая Метка на вашем уровне, и имеет тот же тип урона, что и оружие. Вы можете нанести этот дополнительный урон только один раз в ход.\n\n#### ИЗЛЮБЛЕННЫЙ ВРАГ\n\n**Умение Охотника 7-го уровня**\n\nВ рамках продолжительного отдыха вы можете потратить время на изучение своих исследований и подготовку к встрече с определенным типом монстра.\nВыберите тип врага: Аберрация, Зверь, Небожитель, Конструкт, Дракон, Элементаль, Фея, Исчадие, Великан, Монстр, Слизь, Растение или Нежить. В течение 24 часов существа этого типа совершают броски атаки против вас с помехой. Вы также имеете преимущество на спасброски от очарования, испуга или одержимости ими.\nВ конце вашего следующего продолжительного отдыха вы можете выбрать тот же тип существа или другой тип существа в качестве вашего Излюбленного Врага.\n\n#### НЕТ СПАСЕНЬЯ\n\n**Умение Охотника 11-го уровня**\n\nКогда существо, помеченное вашей мистической меткой, пытается переместиться, вы можете использовать свою реакцию, чтобы магически телепортироваться на расстояние до 30 футов. Если вы телепортируетесь в пространство в пределах досягаемости вашего оружия от цели, вы можете немедленно совершить атаку по возможности в рамках той же реакции.\n\n#### ЩИТ ХИЩНИКА\n\n**Умение Охотника 15-го уровня**\n\nКогда вы получаете урон от существа, которое вы можете видеть, вы можете использовать свою реакцию, чтобы сверхъестественно защитить себя от этого существа на короткое время. Вы имеете сопротивление всему урону, наносимому целью, в течение 1 минуты, включая сопротивление урону, нанесенному спровоцировавшей атакой. Этот эффект заканчивается раньше, если вы становитесь недееспособным.\nПосле использования это умение нельзя использовать снова, пока вы не закончите продолжительный отдых.",
  "hitDie": "d8",
  "savingThrows": [
    "СИЛ",
    "ЛОВ"
  ],
  "proficiencies": {
    "skills": {
      "granted": [],
      "choose": 3,
      "from": [
        "Уход за животными",
        "Атлетика",
        "Проницательность",
        "Расследование",
        "Природа",
        "Восприятие",
        "Скрытность",
        "Выживание"
      ]
    },
    "armor": [
      "Легкие доспехи",
      "средние доспехи",
      "щиты"
    ],
    "weapons": [
      "Простое оружие",
      "воинское оружие"
    ],
    "tools": [
      "На ваш выбор набор травника",
      "инструменты навигатора",
      "инструменты ловушечника"
    ]
  },
  "startingEquipment": {
    "items": [
      "(а) чешуйчатый доспех или (б) кожаный доспех",
      "(а) два коротких меча или (б) два простых оружия",
      "(а) набор исследователя подземелий или (б) набор путешественника",
      "Длинный лук и колчан с 20 стрелами"
    ]
  },
  "levels": [
    {
      "level": 1,
      "proficiencyBonus": "+2",
      "features": [
        "Исследователь",
        "Мистическая Метка"
      ]
    },
    {
      "level": 2,
      "proficiencyBonus": "+2",
      "features": [
        "Воинское Действие",
        "Использование Заклинаний"
      ]
    },
    {
      "level": 3,
      "proficiencyBonus": "+2",
      "features": [
        "Подкласс Следопыта"
      ]
    },
    {
      "level": 4,
      "proficiencyBonus": "+2",
      "features": [
        "Улучшение"
      ]
    },
    {
      "level": 5,
      "proficiencyBonus": "+3",
      "features": [
        "Мультиатака (2/Действие Атаки)"
      ]
    },
    {
      "level": 6,
      "proficiencyBonus": "+3",
      "features": [
        "Усиленная Метка",
        "Мистическая Метка (к6)"
      ]
    },
    {
      "level": 7,
      "proficiencyBonus": "+3",
      "features": [
        "Умение Подкласса"
      ]
    },
    {
      "level": 8,
      "proficiencyBonus": "+3",
      "features": [
        "Улучшение"
      ]
    },
    {
      "level": 9,
      "proficiencyBonus": "+4",
      "features": [
        "Шаг Преследователя"
      ]
    },
    {
      "level": 10,
      "proficiencyBonus": "+4",
      "features": [
        "Героический Дар"
      ]
    },
    {
      "level": 11,
      "proficiencyBonus": "+4",
      "features": [
        "Умение Подкласса"
      ]
    },
    {
      "level": 12,
      "proficiencyBonus": "+4",
      "features": [
        "Улучшение"
      ]
    },
    {
      "level": 13,
      "proficiencyBonus": "+5",
      "features": [
        "Мистическая Метка (к8)"
      ]
    },
    {
      "level": 14,
      "proficiencyBonus": "+5",
      "features": [
        "Острое Чутье"
      ]
    },
    {
      "level": 15,
      "proficiencyBonus": "+5",
      "features": [
        "Умение Подкласса"
      ]
    },
    {
      "level": 16,
      "proficiencyBonus": "+5",
      "features": [
        "Улучшение"
      ]
    },
    {
      "level": 17,
      "proficiencyBonus": "+6",
      "features": [
        "Мистическая Метка (к10)"
      ]
    },
    {
      "level": 18,
      "proficiencyBonus": "+6",
      "features": [
        "Странник"
      ]
    },
    {
      "level": 19,
      "proficiencyBonus": "+6",
      "features": [
        "Улучшение"
      ]
    },
    {
      "level": 20,
      "proficiencyBonus": "+6",
      "features": [
        "Эпический Дар"
      ]
    }
  ],
  "features": [],
  "subclasses": [],
  "type": "class",
  "id": "BFRD:class/sledopyt",
  "slug": "sledopyt",
  "name": "СЛЕДОПЫТ",
  "schemaVersion": "1.0.0",
  "src": {
    "abbr": "BFRD",
    "name": "Black Flag Reference Document",
    "version": "1.0",
    "url": "https://bfrd.net/",
    "license": "Open RPG Creative License (ORC)",
    "hash": "17406b414530c415761ace00b22787d359aa1d9af41c6c35631e230f584a7475"
  },
  "summary": "Как следопыт, вы обладаете следующими особенностями класса.",
  "sourceFile": "input/classes/ranger.md"
}