{
  "description": "### КЛАССОВЫЕ УМЕНИЯ\n\nКак варвар, вы обладаете следующими особенностями класса.\n\n#### ХИТЫ\n\n* **Кость хитов:** 1d12 за уровень варвара.\n* **Хиты на 1-м уровне:** 12 + ваш модификатор ТЕЛ.\n* **Хиты на более высоких уровнях:** 1d12 (или 7) + ваш модификатор ТЕЛ за каждый уровень варвара после 1-го.\n\n#### ВЛАДЕНИЯ\n\n* **Доспехи:** Лёгкие доспехи, средние доспехи, щиты.\n* **Оружие:** Простое оружие, воинское оружие.\n* **Инструменты:** Инструменты травника.\n* **Спасброски:** СИЛ, ТЕЛ.\n* **Навыки:** Выберите два из следующих: Уход за животными, Атлетика, Запугивание, Природа, Внимательность и Выживание.\n\n#### НАЧАЛЬНОЕ СНАРЯЖЕНИЕ\n\nВы начинаете со следующим снаряжением, в дополнение к снаряжению, предоставленному вашей предысторией:\n\n* (a) секира или (b) любое воинское оружие ближнего боя.\n* (a) два ручных топора или (b) любое простое оружие.\n* Набор исследователя и четыре дротика.\nКонечно, вот таблица на русском языке в формате Markdown:\n\n#### ПРОГРЕССИЯ ВАРВАРА\n\n| УРОВЕНЬ | БМ | ЯРОСТЬ | УРОН ЯРОСТИ | УМЕНИЯ |\n| :---: | :-: | :---: | :---: | :--- |\n| 1-й | +2 | 2 | +2 | Ярость, Защита без доспехов |\n| 2-й | +2 | 2 | +2 | Чувство опасности, Безрассудная атака |\n| 3-й | +2 | 3 | +2 | Подкласс варвара |\n| 4-й | +2 | 3 | +2 | Улучшение |\n| 5-й | +3 | 3 | +2 | Быстрое движение, Мультиатака (2/Действие Атаки) |\n| 6-й | +3 | 4 | +2 | Звериный инстинкт |\n| 7-й | +3 | 4 | +2 | Умение подкласса |\n| 8-й | +3 | 4 | +2 | Улучшение |\n| 9-й | +4 | 4 | +3 | Жестокий критический удар (1 кость) |\n| 10-й | +4 | 4 | +3 | Героический дар |\n| 11-й | +4 | 4 | +3 | Умение подкласса |\n| 12-й | +4 | 5 | +3 | Улучшение |\n| 13-й | +5 | 5 | +3 | Жестокий критический удар (2 кости) |\n| 14-й | +5 | 5 | +3 | Неослабевающая ярость |\n| 15-й | +5 | 5 | +3 | Умение подкласса |\n| 16-й | +5 | 5 | +4 | Улучшение |\n| 17-й | +6 | 6 | +4 | Жестокий критический удар (3 кости) |\n| 18-й | +6 | 6 | +4 | Несокрушимая мощь |\n| 19-й | +6 | 6 | +4 | Улучшение |\n| 20-й | +6 | Неограниченно | +5 | Эпический дар |\n\n#### ЯРОСТЬ\n\n**Умение варвара 1-го уровня**\n\nВ бою вы сражаетесь с первобытной свирепостью. В свой ход вы можете войти в ярость в качестве бонусного действия.\n\nВ ярости вы получаете следующие преимущества, если не носите тяжёлую броню:\n\n* У вас есть преимущество при проверках и спасбросках СИЛ.\n* Когда вы совершаете атаку оружием ближнего боя с использованием СИЛ, вы получаете бонус к броску урона, который увеличивается по мере повышения вашего уровня варвара (как показано в столбце «Урон от ярости» в таблице прогрессии варвара). Тип урона этого дополнительного урона соответствует типу оружия, используемого для его нанесения.\n* У вас есть сопротивление дробящему, колющему и рубящему урону.\n\nЕсли вы можете использовать заклинания, вы не можете их использовать или концентрироваться на них, находясь в ярости.\n\nВаша ярость длится 1 минуту. Она заканчивается раньше, если вы нокаутированы или если ваш ход заканчивается, и вы не атаковали враждебное существо или не получили урон от враждебного существа с начала вашего последнего хода. Вы также можете закончить свою ярость раньше бонусным действием в свой ход.\n\nВы можете входить в ярость количество раз, равное числу, указанному в таблице прогрессии варвара. Вы восстанавливаете все израсходованные применения ярости, когда заканчиваете продолжительный отдых.\n\n#### ЗАЩИТА БЕЗ ДОСПЕХОВ\n\n**Умение варвара 1-го уровня**\n\nКогда вы не носите доспехи, ваш КД равен 13 + ваш модификатор ТЕЛ. (ЛОВ не учитывается при расчете КД для этой особенности класса.) Вы можете использовать щит и по-прежнему получать эту выгоду.\n\n#### ЧУВСТВО ОПАСНОСТИ\n\n**Умение варвара 2-го уровня**\n\nВы обретаете сверхъестественное чувство надвигающейся опасности, что даёт вам преимущество при уклонении от вреда. У вас есть преимущество при спасбросках ЛОВ, если вы не ослеплены, не оглушены и не выведены из строя.\n\n#### БЕЗРАССУДНАЯ АТАКА\n\n**Умение варвара 2-го уровня**\n\nВы можете отбросить заботу об обороне в пользу яростной атаки. Когда вы совершаете атаку в свой ход, вы можете решить сделать это безрассудно. Это даёт вам преимущество при бросках атаки оружием ближнего боя с использованием СИЛ в течение этого хода, но броски атаки против вас имеют преимущество до начала вашего следующего хода.\n\n#### УМЕНИЯ ПОДКЛАССА ВАРВАРА\n\n**Умение варвара 3-го, 7-го, 11-го и 15-го уровней*\n\nВыберите подкласс, который отражает ваш путь, будь то Берсерк или Дикая Ярость (подробно описаны в конце этого класса). Ваш выбор даёт вам особенности на 3-м, 7-м, 11-м и 15-м уровнях.\n\n#### УЛУЧШЕНИЕ\n\n**Умение варвара 4-го, 8-го, 12-го, 16-го и 19-го уровней*\n\nВыберите одно из следующих улучшений (значения характеристик не могут быть повышены выше 20 с помощью этой особенности):\n\n* Увеличьте одну характеристику на 2.\n* Увеличьте две разные характеристики на 1 каждую.\n* Увеличьте одну характеристику на 1 и выберите талант из списка воинских талантов.\n\n#### БЫСТРОЕ ПЕРЕДВИЖЕНИЕ\n\n**Умение варвара 5-го уровня**\n\nВаша скорость увеличивается на 10 футов, когда вы не носите тяжёлую броню. Кроме того, когда вы бросаете инициативу, вы можете немедленно переместиться на половину своей скорости.\n\n#### МУЛЬТИАТАКА\n\n**Умение варвара 5-го уровня**\n\nВаше физическое мастерство возросло. В свой ход вы можете совершить две атаки, когда совершаете действие \"Атака\".\n\n#### ЗВЕРИНЫЙ ИНСТИНКТ\n\n**Умение варвара 6-го уровня**\n\nВаши отточенные инстинкты дают вам преимущество при бросках инициативы. Кроме того, если вы застигнуты врасплох в начале боя и не выведены из строя, вы можете действовать нормально в свой первый ход, если вы войдете в ярость, прежде чем делать что-либо еще в этот ход.\n\n#### ЖЕСТОКИЙ КРИТИЧЕСКИЙ УДАР\n\n**Умение варвара 9-го, 13-го и 17-го уровней*\n\nВы наносите критический удар при броске d20 19 или 20 оружием ближнего боя и безоружными ударами. Вы также бросаете одну дополнительную кость урона от оружия при определении дополнительного урона за критический удар при атаке ближнего боя.\n\nЭтот дополнительный урон увеличивается до двух дополнительных костей на 13-м уровне и до трех дополнительных костей на 17-м уровне.\n\n#### ГЕРОИЧЕСКОЕ БЛАГОСЛОВЕНИЕ\n\n**Умение варвара 10-го уровня**\n\nВаша приверженность пути варвара дарует вам мощную способность. Выберите одно из следующих героических благословений:\n\n* **Мгновенная ярость.** Вы можете войти в ярость (не требуется бонусное действие), когда вы бросаете инициативу и используете свою особенность \"Быстрое передвижение\", если у вас осталось хотя бы одно использование ярости.\n* **Упрямая ярость.** Ваша ярость заканчивается только тогда, когда истекает её продолжительность, вы теряете сознание или решаете её закончить.\n\n#### БЕЗЖАЛОСТНАЯ ЯРОСТЬ\n\n**Умение варвара 14-го уровня**\n\nВаша ярость позволяет вам отмахнуться даже от смертельных ран. В ярости, если вас опустили до 0 хитов, вы можете совершить спасбросок ТЕЛ СЛ 10. При успехе вы не теряете сознание до окончания вашей текущей ярости. Вы по-прежнему совершаете спасброски от смерти и можете быть убиты, если получите урон от одного источника, равный вашему максимальному количеству хитов.\n\nДаже если вы провалите три спасброска от смерти во время вашей ярости, вы умрете, только если закончите свой ход с 0 хитами.\n\nКаждый раз, когда вы используете эту особенность после первого, СЛ увеличивается на 5. Когда вы заканчиваете короткий или продолжительный отдых, СЛ сбрасывается до 10.\n\n#### НЕПОКОЛЕБИМАЯ МОЩЬ\n\n**Умение варвара 18-го уровня**\n\nВы усовершенствовали применение мощи и храбрости. Вы получаете следующие преимущества:\n\n* Когда вы совершаете проверку характеристики или спасбросок с использованием СИЛ или ТЕЛ, считайте любой бросок d20 9 или ниже как 10.\n* Ваши атаки оружием ближнего боя наносят дополнительный урон, равный вашему значению СИЛ, предметам и структурам.\n\n#### ЭПИЧЕСКОЕ БЛАГОСЛОВЕНИЕ\n\n**Умение варвара 20-го уровня**\n\nВаша приверженность пути варвара дарует вам мощную новую способность. Вы получаете следующее эпическое благословение:\n\n* **Первобытный чемпион.** Вы воплощаете необузданную силу. Ваши значения СИЛ и ТЕЛ увеличиваются на 4 каждое. Ваш максимум для этих значений теперь равен 24.\n\n### ПОДКЛАСС: \"БЕРСЕРК\"\n\nЧерез первобытный обряд или естественную жажду крови некоторые варвары могут довести себя до такой свирепой ярости и взрывоопасного насилия, что рискуют сломать своё тело. Берсерки могут потеряться в своём безумии, кипящей необузданной жестокостью, принимая залитое кровью поле битвы, не заботясь о собственной безопасности.\n\n#### ПРОГРЕССИЯ БЕРСЕРКА\n\n| УРОВЕНЬ ВАРВАРА | УМЕНИЯ |\n|---|---|\n| 3-й | Безумие, Безжалостное поведение |\n| 7-й | Безрассудная ярость |\n| 11-й | Пугающее присутствие |\n| 15-й | Возмездие |\n\n#### БЕЗУМИЕ\n\n**Умение берсерка 3-го уровня**\n\nВы можете войти в безумие как часть бонусного действия, которое вы используете для активации своей особенности \"Ярость\". Как только вы это сделаете, на время его действия вы можете совершать одну атаку оружием ближнего боя в качестве бонусного действия в каждый из своих ходов.\n\n#### БЕЗЖАЛОСТНОЕ ПОВЕДЕНИЕ\n\n**Умение берсерка 3-го уровня**\n\nВаша свирепость всегда маячит. Вы получаете владение навыком Запугивание. Если вы уже владеете этим навыком, удвойте свой БМ вместо проверок Запугивания.\n\n#### БЕЗРАССУДНАЯ ЯРОСТЬ\n\n**Умение берсерка 7-го уровня**\n\nВ ярости вы получаете следующие преимущества:\n\n* Вы игнорируете любые уровни истощения, которые у вас в настоящее время есть, на время действия вашей ярости.\n* Вы не можете быть очарованы или напуганы, находясь в ярости.\n\nЕсли вы уже очарованы или напуганы, когда входите в ярость, эффект приостанавливается на время действия ярости.\n\n* Во время Безумия, если вы наносите критический удар или опускаете существо до 0 ХП, вы получаете количество временных ХП, равное вашему БМ + ваш модификатор ТЕЛ. Эти хиты действуют до тех пор, пока не будут израсходованы или пока вы не закончите короткий или продолжительный отдых.\n\n#### ПУГАЮЩЕЕ ПРИСУТСТВИЕ\n\n**Умение берсерка 11-го уровня**\n\nВаши атаки оружием наносят количество дополнительного урона, равное вашему БМ (того же типа урона, что и оружие), испуганным существам.\n\nКроме того, в качестве бонусного действия вы можете попытаться напугать количество существ (до вашего БВ), находящихся в пределах 30 футов от вас, которые могут видеть или слышать вас. Каждая цель должна совершить спасбросок МДР (СЛ 8 + ваш БМ + ваш модификатор ХАР + количество временных ХП, которые у вас в настоящее время есть от вашей особенности \"Безрассудная ярость\"). При провале существо испугано вас до конца вашего следующего хода.\n\nВ последующие ходы вы можете использовать своё бонусное действие, чтобы продлить продолжительность этого эффекта на каждое испуганное существо до конца вашего следующего хода. Этот эффект заканчивается, если существо заканчивает свой ход на расстоянии более 60 футов от вас или больше не может видеть или слышать вас.\n\nЕсли существо преуспевает в своем спасении, вы не можете использовать эту особенность на этом существе снова в течение 24 часов.\n\n#### ВОЗМЕЗДИЕ\n\n**Умение берсерка 15-го уровня**\n\nКогда существо попадает в вас или промахивается по вам атакой, вы можете использовать свою реакцию, чтобы переместиться на половину своей скорости в сторону этого существа и совершить одну атаку ближнего боя против него. Если существо имеет размер Большой или больше, у вас есть преимущество при броске атаки.",
  "hitDie": "d12",
  "savingThrows": [
    "СИЛ",
    "ТЕЛ"
  ],
  "proficiencies": {
    "skills": {
      "granted": [],
      "choose": 2,
      "from": [
        "Уход за животными",
        "Атлетика",
        "Запугивание",
        "Природа",
        "Внимательность",
        "Выживание"
      ]
    },
    "armor": [
      "Лёгкие доспехи",
      "средние доспехи",
      "щиты"
    ],
    "weapons": [
      "Простое оружие",
      "воинское оружие"
    ],
    "tools": [
      "Инструменты травника"
    ]
  },
  "startingEquipment": {
    "items": [
      "(a) секира или (b) любое воинское оружие ближнего боя.",
      "(a) два ручных топора или (b) любое простое оружие.",
      "Набор исследователя и четыре дротика.Конечно, вот таблица на русском языке в формате Markdown:"
    ]
  },
  "levels": [
    {
      "level": 1,
      "proficiencyBonus": "+2",
      "features": [
        "Ярость",
        "Защита без доспехов"
      ]
    },
    {
      "level": 2,
      "proficiencyBonus": "+2",
      "features": [
        "Чувство опасности",
        "Безрассудная атака"
      ]
    },
    {
      "level": 3,
      "proficiencyBonus": "+2",
      "features": [
        "Подкласс варвара"
      ]
    },
    {
      "level": 4,
      "proficiencyBonus": "+2",
      "features": [
        "Улучшение"
      ]
    },
    {
      "level": 5,
      "proficiencyBonus": "+3",
      "features": [
        "Быстрое движение",
        "Мультиатака (2/Действие Атаки)"
      ]
    },
    {
      "level": 6,
      "proficiencyBonus": "+3",
      "features": [
        "Звериный инстинкт"
      ]
    },
    {
      "level": 7,
      "proficiencyBonus": "+3",
      "features": [
        "Умение подкласса"
      ]
    },
    {
      "level": 8,
      "proficiencyBonus": "+3",
      "features": [
        "Улучшение"
      ]
    },
    {
      "level": 9,
      "proficiencyBonus": "+4",
      "features": [
        "Жестокий критический удар (1 кость)"
      ]
    },
    {
      "level": 10,
      "proficiencyBonus": "+4",
      "features": [
        "Героический дар"
      ]
    },
    {
      "level": 11,
      "proficiencyBonus": "+4",
      "features": [
        "Умение подкласса"
      ]
    },
    {
      "level": 12,
      "proficiencyBonus": "+4",
      "features": [
        "Улучшение"
      ]
    },
    {
      "level": 13,
      "proficiencyBonus": "+5",
      "features": [
        "Жестокий критический удар (2 кости)"
      ]
    },
    {
      "level": 14,
      "proficiencyBonus": "+5",
      "features": [
        "Неослабевающая ярость"
      ]
    },
    {
      "level": 15,
      "proficiencyBonus": "+5",
      "features": [
        "Умение подкласса"
      ]
    },
    {
      "level": 16,
      "proficiencyBonus": "+5",
      "features": [
        "Улучшение"
      ]
    },
    {
      "level": 17,
      "proficiencyBonus": "+6",
      "features": [
        "Жестокий критический удар (3 кости)"
      ]
    },
    {
      "level": 18,
      "proficiencyBonus": "+6",
      "features": [
        "Несокрушимая мощь"
      ]
    },
    {
      "level": 19,
      "proficiencyBonus": "+6",
      "features": [
        "Улучшение"
      ]
    },
    {
      "level": 20,
      "proficiencyBonus": "+6",
      "features": [
        "Эпический дар"
      ]
    }
  ],
  "features": [],
  "subclasses": [],
  "type": "class",
  "id": "BFRD:class/varvar",
  "slug": "varvar",
  "name": "ВАРВАР",
  "schemaVersion": "1.0.0",
  "src": {
    "abbr": "BFRD",
    "name": "Black Flag Reference Document",
    "version": "1.0",
    "url": "https://bfrd.net/",
    "license": "Open RPG Creative License (ORC)",
    "hash": "3fbe021dff426738fa88b3841dd01a5705fab4b9c23688a694278648ccaf2c70"
  },
  "summary": "Как варвар, вы обладаете следующими особенностями класса.",
  "sourceFile": "input/classes/barbarian.md"
}