{
  "description": "### КЛАССОВЫЕ УМЕНИЯ\n\nКак воин, вы обладаете следующими особенностями класса.\n\n#### ХИТЫ\n\n* **Кость хитов:** 1d10 за уровень воина.\n* **Хиты на 1-м уровне:** 10 + ваш модификатор ТЕЛ.\n* **Хиты на более высоких уровнях:** 1d10 (или 6) + ваш модификатор ТЕЛ за каждый уровень воина после 1-го.\n\n#### ВЛАДЕНИЯ\n\n* **Доспехи:** Все доспехи и щиты.\n* **Оружие:** Простое оружие, воинское оружие.\n* **Инструменты:** Нет.\n* **Спасброски:** СИЛ, ТЕЛ.\n* **Навыки:** Выберите два из следующих: Акробатика, Уход за животными, Атлетика, История, Проницательность, Запугивание, Внимательность и Выживание.\n\n#### НАЧАЛЬНОЕ СНАРЯЖЕНИЕ\n\nВы начинаете со следующим снаряжением, в дополнение к снаряжению, предоставленному вашей предысторией:\n\n* (a) кольчуга или (b) кожаный доспех, длинный лук и 20 стрел.\n* (a) воинское оружие и щит или (b) два воинских оружия.\n* (a) лёгкий арбалет и 20 болтов или (b) два ручных топора.\n* (a) набор исследователя подземелий или (b) набор исследователя.\n\n#### ПРОГРЕССИЯ ВОИНА\n\n| УРОВЕНЬ | БМ | УМЕНИЯ |\n|---|---|---|\n| 1-й | +2 | Последний рубеж, Воинское действие |\n| 2-й | +2 | Всплеск действия |\n| 3-й | +2 | Подкласс воина |\n| 4-й | +2 | Улучшение |\n| 5-й | +3 | Мультиатака (2/Действие \"Атака\") |\n| 6-й | +3 | Улучшение |\n| 7-й | +3 | Особенность подкласса |\n| 8-й | +3 | Улучшение |\n| 9-й | +4 | Мультиатака (3/Действие \"Атака\") |\n| 10-й | +4 | Героическое благословение |\n| 11-й | +4 | Особенность подкласса |\n| 12-й | +4 | Улучшение |\n| 13-й | +5 | Всплеск действия (2/Отдых) |\n| 14-й | +5 | Улучшение |\n| 15-й | +5 | Особенность подкласса |\n| 16-й | +5 | Улучшение |\n| 17-й | +6 | Мультиатака (4/Действие \"Атака\") |\n| 18-й | +6 | Всплеск действия (3/Отдых) |\n| 19-й | +6 | Улучшение |\n| 20-й | +6 | Эпическое благословение |\n\n#### ПОСЛЕДНИЙ РУБЕЖ\n\n**Умение воина 1-го уровня**\n\nКогда вы получаете урон, который может уменьшить ваши хиты до менее половины вашего максимального количества хитов (округленного в меньшую сторону), вы можете использовать свою реакцию, чтобы потратить кости хитов, до числа, равного вашему БМ. Немедленно бросьте эти кости хитов. Вы восстанавливаете хиты, равные сумме всех брошенных костей + ваш модификатор ТЕЛ.\n\n#### ВОИНСКОЕ ДЕЙСТВИЕ\n\n**Умение воина 1-го уровня**\n\nВаш тактический опыт позволяет вам быстро действовать на поле боя. Вы можете совершать бонусное действие в каждый свой ход в бою, чтобы выполнить опцию оружия или одно из воинских действий, предоставленных этой особенностью.\n\nВыберите одно из следующих воинских действий, которые вы знаете.\n\n##### Прицеливание\n\n*Требуется владение дальнобойным или метательным оружием*\n\nВ качестве бонусного действия вы тратите время, чтобы повысить эффективность своей следующей атаки дальнобойным оружием. Выберите одну цель, которую вы видите. Если вы совершите атаку дальнобойным оружием против этой цели до конца своего хода, удвойте свой БМ для первого броска атаки.\n\n##### Охрана\n\n*Требуется владение щитом*\n\nВ качестве бонусного действия вы поднимаете свой щит, чтобы перехватывать входящие атаки. Выберите одно вражеское существо в пределах 5 футов от вас. Это существо получает недостаток при первом броске атаки, которое оно совершает против вас или союзника в пределах 5 футов от вас до начала вашего следующего хода.\n\n##### Быстрая атака\n\n*Требуется владение двумя лёгкими оружиями*\n\nПосле того, как вы совершаете действие \"Атака\" в свой ход и атакуете Лёгким оружием ближнего боя, которое вы держите в одной руке, вы можете использовать бонусное действие, чтобы совершить две атаки другим Лёгким оружием ближнего боя, которое вы держите в другой руке — вместо одной атаки, обычно предоставляемой сражением двумя оружиями. Не добавляйте свой модификатор характеристики к урону этих дополнительных атак, если модификатор не является отрицательным.\n\n##### Замах\n\n*Требуется владение двуручным тяжёлым или универсальным оружием ближнего боя*\n\nВ качестве бонусного действия вы подготавливаете мощную атаку против находящейся поблизости цели. Выберите одну цель, которую вы видите в пределах 10 футов от вас. Если вы попадёте в эту цель атакой оружием ближнего боя до конца своего хода, первая такая атака нанесёт дополнительный урон, равный вашему БМ (того же типа урона, что и оружие).\n\n#### ВСПЛЕСК ДЕЙСТВИЯ\n\n**Умение воина 2-го, 13-го и 18-го уровней*\n\nКогда потребность велика, вы доводите своё тело до абсолютного предела. В свой ход вы можете активировать эту особенность, чтобы получить ещё одно действие — в дополнение к действию и возможному бонусному действию, которые вы регулярно получаете в свой ход.\n\nПосле того, как вы используете эту особенность, вы должны завершить короткий или продолжительный отдых, прежде чем сможете использовать её снова. Начиная с 13-го уровня, вы можете использовать её дважды перед отдыхом, но только один раз в тот же ход. На 18-м уровне вы можете использовать её три раза перед отдыхом, но только один раз в тот же ход.\n\n#### УМЕНИЯ ПОДКЛАССА ВОИНА\n\n**Умение воина 3-го, 7-го, 11-го и 15-го уровней*\n\nВыберите подкласс, который отражает вашу роль в битве, либо Магический клинок, либо Мастер оружия (подробно описаны в конце этого класса). Ваш выбор предоставляет вам особенности на 3-м, 7-м, 11-м и 15-м уровнях.\n\n#### УЛУЧШЕНИЕ\n\n**Умение воина 4-го, 6-го, 8-го, 12-го, 14-го, 16-го и 19-го уровней*\n\nВыберите одно из следующих улучшений (значения характеристик не могут быть повышены выше 20 с помощью этой особенности):\n\n* Увеличьте одну характеристику на 2.\n* Увеличьте две разные характеристики на 1 каждую.\n* Увеличьте одну характеристику на 1 и выберите талант из списка воинских талантов.\n\n#### МУЛЬТИАТАКА\n\n**Умение воина 5-го, 9-го и 17-го уровней*\n\nВаше физическое мастерство возросло. В свой ход вы можете совершить две атаки, когда совершаете действие \"Атака\".\n\nНачиная с 9-го уровня, вы можете совершить три атаки, когда совершаете действие \"Атака\". На 17-м уровне вы можете совершить четыре атаки.\n\n#### ГЕРОИЧЕСКОЕ БЛАГОСЛОВЕНИЕ\n\n**Умение воина 10-го уровня**\n\nВаша приверженность пути воина дарует вам мощную новую способность. Выберите одно из следующих героических благословений:\n\n* **Непокорный.** Когда вы проваливаете спасение, вы можете вместо этого выбрать успех в спасении. Вы можете использовать эту особенность один раз и восстановить её использование, когда завершите продолжительный отдых. Вы можете использовать её дважды перед продолжительным отдыхом на 13-м уровне и трижды на 17-м.\n* **Неудержимый.** Когда вы начинаете свой ход, вы можете выбрать прекращение одного из следующих состояний, поразивших вас: ослеплённый, очарованный, испуганный, выведенный из строя, парализованный или оглушённый. Вы можете использовать эту особенность количество раз, равное вашему БМ, и вы восстанавливаете все израсходованные использования, когда завершите продолжительный отдых.\n\n#### ЭПИЧЕСКОЕ БЛАГОСЛОВЕНИЕ\n\n**Умение воина 20-го уровня**\n\nВаша приверженность пути воина дарует вам мощную новую способность. Вы получаете следующее эпическое благословение:\n\n* **Переломить ход битвы.** Один раз в каждый из своих ходов, когда вы попадаете в существо или объект атакой оружием в свой ход, вы можете заставить атаку нанести дополнительный урон (того же типа урона, что и оружие), равный вашему значению СИЛ или ЛОВ (по вашему выбору). Урон атаки игнорирует сопротивление и иммунитет, и его нельзя уменьшить или избежать никакими средствами.\n\n### ПОДКЛАСС: МАСТЕР ОРУЖИЯ\n\nБольшинство воинов чувствуют глубокую связь со своим оружием, но никто больше, чем Мастер оружия. Для них любимый лук или клинок является естественным продолжением их тела и надёжным союзником. Воины, которые преследуют этот подкласс, учатся использовать выбранное ими оружие с эффективностью и мастерством.\n\n#### ПРОГРЕССИЯ МАСТЕРА ОРУЖИЯ\n\n| УРОВЕНЬ ВОИНА | УМЕНИЯ |\n|---|---|\n| 3-й | Мастерство, Трюки |\n| 7-й | Смертельный росчерк |\n| 11-й | Продвинутые трюки |\n| 15-й | Грандиозный финал |\n\n#### МАСТЕРСТВО\n\n**Умение Мастера оружия 3-го уровня**\n\nВыберите три типа простого или воинского оружия, которыми вы владеете. Вы овладели использованием этих трёх оружий.\n\nОдин раз за ход, когда вы бросаете урон для атаки оружием, которым вы овладели, вы можете перебросить кости урона оружия и использовать любой результат.\n\nВ качестве альтернативы, один раз за ход, когда вы используете опцию оружия для оружия, которым вы овладели, вы можете бросить урон атаки, даже если опция оружия обычно не позволяет этого.\n\n#### ТРЮКИ\n\n**Умение Мастера оружия 3-го уровня**\n\nВ рамках вашей тренировки вы научились использовать уникальную тактику с определённым оружием. Вы получаете доступ к специальным манёврам, называемым трюками.\n\nЧтобы использовать трюк, вы должны владеть оружием, которое соответствует типу оружия, указанному в описании трюка (если он указан). Вы можете использовать только один трюк за ход. Вы получаете доступ к продвинутым трюкам на более высоких уровнях.\n\nВсе перечисленные трюки доступны вам на 3-м уровне. Вы можете выполнять трюки количество раз, равное вашему БМ + 1. После этого вы должны завершить короткий или продолжительный отдых, чтобы восстановить израсходованные использования.\n\n##### Спасения.\n\nНекоторые трюки требуют, чтобы ваша цель совершила спасение, чтобы противостоять его эффектам. СЛ спасения для этих трюков рассчитывается следующим образом:\n\n*СЛ спасения от трюка = 8 + ваш бонус мастерства (БМ) + ваш модификатор СИЛ или ЛОВ (по вашему выбору)*\n\nТрюки представлены в алфавитном порядке.\n\n##### Дуговая атака\n\n*Требуется тяжёлое оружие ближнего боя*\n\nКогда вы наносите урон тяжёлым оружием, которым владеете обеими руками, вы можете также нанести половину урона, который вы нанесли, другой цели в пределах досягаемости, которую вы видите. Если вторая цель является объектом, она получает полный урон вместо этого. Вы можете решить использовать это после того, как узнаете свой бросок урона.\n\n##### Грязный приём\n\n*Требуется оружие ближнего боя*\n\nКогда вы успешно попадаете в цель оружием ближнего боя как часть действия \"Атака\", вы можете немедленно совершить безоружный удар против этой цели как часть того же действия \"Атака\".\n\n##### Сделать так, чтобы это было важно\n\nКогда вы совершаете действие \"Атака\", вы можете совершить одну атаку оружием с +10 к броску атаки. При попадании атака наносит дополнительный урон, равный вашему уровню воина. Вы не можете совершать дополнительные атаки как часть этого действия \"Атака\", даже если такая особенность, как \"Мультиатака\", обычно позволяла бы вам это сделать.\n\n##### Парирование\n\n*Требуется оружие ближнего боя*\n\nКогда существо, которое вы можете видеть, попадает в вас атакой оружием, вы можете использовать свою реакцию, чтобы уменьшить урон, который вы получаете, на 1d10 + ваш БМ (до минимума 0 урона).\n\n##### Перенаправление\n\nКогда вы промахиваетесь по цели атакой оружием, вы можете использовать свою реакцию, чтобы немедленно перебросить атаку, но вы должны выбрать другую цель, которую вы видите в пределах 5 футов от исходной цели.\n\n##### Рипост\n\n*Требуется оружие ближнего боя*\n\nКогда существо, которое вы можете видеть в пределах досягаемости, промахивается по вам атакой оружием, вы можете использовать свою реакцию, чтобы немедленно совершить атаку оружием ближнего боя против этого существа.\n\n##### Прямо насквозь\n\n*Требуется дальнобойное оружие*\n\nКогда вы наносите урон атакой дальнобойным оружием, вы можете также нанести половину урона, который вы нанесли, другой цели, которую вы видите в пределах 5 футов от исходной цели. Вы можете решить использовать это после того, как узнаете свой бросок урона.\n\n##### Тактическое отступление\n\n*Требуется оружие ближнего боя*\n\nКогда вы попадаете в существо оружием как часть действия \"Атака\", вы можете немедленно переместиться на половину своей скорости как часть того же действия, не провоцируя внеочередные атаки.\n\n#### СМЕРТЕЛЬНЫЙ РОСЧЕРК\n\n**Умение Мастера оружия 7-го уровня**\n\nАтаки, совершённые с оружием, которым вы овладели благодаря своей особенности \"Мастерство\", наносят критические удары при броске 19 или 20. Когда вы наносите критический удар, вы можете использовать свою реакцию, чтобы сделать одно из следующего:\n\n* Совершить атаку дальнобойным оружием против количества существ, равного вашему БМ, в пределах 15 футов от цели, поражённой вашим критическим ударом.\n* Совершить отдельную атаку ближнего боя против каждого существа в пределах 5 футов от вас.\n\n#### ПРОДВИНУТЫЕ ТРЮКИ\n\n**Умение Мастера оружия 11-го уровня**\n\nСледующие мощные трюки доступны вам всякий раз, когда вы могли бы использовать трюк.\n\n##### Засада убийцы\n\nКогда вы попадаете в существо, от которого вы скрыты, атакой оружием, бросьте кости урона от вашего оружия дважды вместо одного раза. При критическом ударе бросьте кости урона оружия три раза вместо двух раз.\n\n##### Бастион\n\n*Требуется щит*\n\nКогда вы получаете урон от заклинания или способности, которая требует спасения, например, заклинание \"огненный шар\", вы можете использовать свою реакцию, чтобы уменьшить нанесённый вам урон на сумму, равную вашему КД. Психический урон нельзя уменьшить с помощью этого трюка.\n\n##### Крушащий удар\n\n*Требуется тяжёлое оружие ближнего боя*\n\nВ качестве действия вы можете совершить одиночную атаку ближнего боя, нацеленную на каждое существо в пределах досягаемости, используя единый бросок атаки и урона.\n\n##### Превентивный удар\n\n*Требуется оружие ближнего боя*\n\nКогда существо приближается в пределах досягаемости вашего оружия, вы можете использовать свою реакцию, чтобы совершить одиночную атаку против него. При попадании скорость цели уменьшается на 15 футов до начала вашего следующего хода.\n\n##### Быстрый выстрел\n\n*Требуется дальнобойное или метательное оружие*\n\nПосле того, как вы совершите действие \"Атака\", вы можете использовать бонусное действие, чтобы совершить дополнительную атаку дальнобойным или метательным оружием. Вы можете вытащить метательное оружие как часть атаки.\n\n##### Захват борца\n\n*Требуется оружие ближнего боя*\n\nКогда вы попадаете в существо атакой ближнего боя, существо должно преуспеть в спасении СИЛ или быть захваченным вами. Пока эта схватка сохраняется, трюки, которые вы используете против захваченного существа, не расходуют использования вашей особенности \"Трюки\". Эта схватка заканчивается, если вы атакуете другое существо, цель сбегает или вы прекращаете её (никаких действий не требуется).\n\n#### ГРАНДИОЗНЫЙ ФИНАЛ\n\n**Умение Мастера оружия 15-го уровня**\n\nКогда вы бросаете инициативу и у вас не осталось использований вашей особенности \"Трюки\", вы можете восстановить 3 использования. Вы должны завершить продолжительный отдых, прежде чем сможете использовать эту особенность снова.",
  "hitDie": "d10",
  "savingThrows": [
    "СИЛ",
    "ТЕЛ"
  ],
  "proficiencies": {
    "skills": {
      "granted": [],
      "choose": 2,
      "from": [
        "Акробатика",
        "Уход за животными",
        "Атлетика",
        "История",
        "Проницательность",
        "Запугивание",
        "Внимательность",
        "Выживание"
      ]
    },
    "armor": [
      "Все доспехи",
      "щиты"
    ],
    "weapons": [
      "Простое оружие",
      "воинское оружие"
    ],
    "tools": [
      "Нет"
    ]
  },
  "startingEquipment": {
    "items": [
      "(a) кольчуга или (b) кожаный доспех, длинный лук и 20 стрел.",
      "(a) воинское оружие и щит или (b) два воинских оружия.",
      "(a) лёгкий арбалет и 20 болтов или (b) два ручных топора.",
      "(a) набор исследователя подземелий или (b) набор исследователя."
    ]
  },
  "levels": [
    {
      "level": 1,
      "proficiencyBonus": "+2",
      "features": [
        "Последний рубеж",
        "Воинское действие"
      ]
    },
    {
      "level": 2,
      "proficiencyBonus": "+2",
      "features": [
        "Всплеск действия"
      ]
    },
    {
      "level": 3,
      "proficiencyBonus": "+2",
      "features": [
        "Подкласс воина"
      ]
    },
    {
      "level": 4,
      "proficiencyBonus": "+2",
      "features": [
        "Улучшение"
      ]
    },
    {
      "level": 5,
      "proficiencyBonus": "+3",
      "features": [
        "Мультиатака (2/Действие \"Атака\")"
      ]
    },
    {
      "level": 6,
      "proficiencyBonus": "+3",
      "features": [
        "Улучшение"
      ]
    },
    {
      "level": 7,
      "proficiencyBonus": "+3",
      "features": [
        "Особенность подкласса"
      ]
    },
    {
      "level": 8,
      "proficiencyBonus": "+3",
      "features": [
        "Улучшение"
      ]
    },
    {
      "level": 9,
      "proficiencyBonus": "+4",
      "features": [
        "Мультиатака (3/Действие \"Атака\")"
      ]
    },
    {
      "level": 10,
      "proficiencyBonus": "+4",
      "features": [
        "Героическое благословение"
      ]
    },
    {
      "level": 11,
      "proficiencyBonus": "+4",
      "features": [
        "Особенность подкласса"
      ]
    },
    {
      "level": 12,
      "proficiencyBonus": "+4",
      "features": [
        "Улучшение"
      ]
    },
    {
      "level": 13,
      "proficiencyBonus": "+5",
      "features": [
        "Всплеск действия (2/Отдых)"
      ]
    },
    {
      "level": 14,
      "proficiencyBonus": "+5",
      "features": [
        "Улучшение"
      ]
    },
    {
      "level": 15,
      "proficiencyBonus": "+5",
      "features": [
        "Особенность подкласса"
      ]
    },
    {
      "level": 16,
      "proficiencyBonus": "+5",
      "features": [
        "Улучшение"
      ]
    },
    {
      "level": 17,
      "proficiencyBonus": "+6",
      "features": [
        "Мультиатака (4/Действие \"Атака\")"
      ]
    },
    {
      "level": 18,
      "proficiencyBonus": "+6",
      "features": [
        "Всплеск действия (3/Отдых)"
      ]
    },
    {
      "level": 19,
      "proficiencyBonus": "+6",
      "features": [
        "Улучшение"
      ]
    },
    {
      "level": 20,
      "proficiencyBonus": "+6",
      "features": [
        "Эпическое благословение"
      ]
    }
  ],
  "features": [],
  "subclasses": [],
  "type": "class",
  "id": "BFRD:class/voin",
  "slug": "voin",
  "name": "ВОИН",
  "schemaVersion": "1.0.0",
  "src": {
    "abbr": "BFRD",
    "name": "Black Flag Reference Document",
    "version": "1.0",
    "url": "https://bfrd.net/",
    "license": "Open RPG Creative License (ORC)",
    "hash": "53dffe649d52bb9c8e266bff026e88b1d0adf31d66c3812489feafa667dc0744"
  },
  "summary": "Как воин, вы обладаете следующими особенностями класса.",
  "sourceFile": "input/classes/fighter.md"
}