{
  "description": "### КЛАССОВЫЕ УМЕНИЯ\n\nКак жрец, вы обладаете следующими особенностями класса.\n\n#### ХИТЫ\n\n* **Кость хитов:** 1d8 за уровень жреца.\n* **Хиты на 1-м уровне:** 8 + ваш модификатор ТЕЛ.\n* **Хиты на более высоких уровнях:** 1d8 (или 5) + ваш модификатор ТЕЛ за каждый уровень жреца после 1-го.\n\n#### ВЛАДЕНИЯ\n\n* **Доспехи:** Лёгкие доспехи, средние доспехи, щиты.\n* **Оружие:** Простое оружие.\n* **Инструменты:** Нет.\n* **Спасброски:** МДР, ХАР.\n* **Навыки:** Выберите два из следующих: История, Проницательность, Медицина, Убеждение и Религия.\n\n#### НАЧАЛЬНОЕ СНАРЯЖЕНИЕ\n\nВы начинаете со следующим снаряжением, в дополнение к снаряжению, предоставленному вашей предысторией:\n\n* (a) булава или (b) боевой молот (если владеете).\n* (a) чешуйчатый доспех, (b) кожаный доспех или (c) кольчуга (если владеете).\n* (a) лёгкий арбалет и 20 болтов или (b) любое простое оружие.\n* (a) набор священника или (b) набор исследователя.\n* Щит и священный символ.\n\n#### ПРОГРЕССИЯ ЖРЕЦА\n\n| УРОВЕНЬ | БМ | УМЕНИЯ | ИЗВЕСТНЫЕ ЗАГОВОРЫ | ИЗВЕСТНЫЕ РИТУАЛЫ | 1-й | 2-й | 3-й | 4-й | 5-й | 6-й | 7-й | 8-й | 9-й |\n| :---: | :-: | :--- | :---: | :---: | :-: | :-: | :-: | :-: | :-: | :-: | :-: | :-: | :-: |\n| 1-й | +2 | Проявление Веры, Использование Заклинаний | 3 | 1 | 2 | — | — | — | — | — | — | — | — |\n| 2-й | +2 | Божественный Канал: Изгнание Нечисти (1/Отдых) | 3 | 1 | 3 | — | — | — | — | — | — | — | — |\n| 3-й | +2 | Подкласс Жреца | 3 | 2 | 4 | 2 | — | — | — | — | — | — | — |\n| 4-й | +2 | Улучшение | 4 | 2 | 4 | 3 | — | — | — | — | — | — | — |\n| 5-й | +3 | Уничтожение Нечисти (ПО 1/2) | 4 | 3 | 4 | 3 | 2 | — | — | — | — | — | — |\n| 6-й | +3 | Божественный Канал (2/Отдых) | 4 | 3 | 4 | 3 | 3 | — | — | — | — | — | — |\n| 7-й | +3 | Умение Подкласса | 4 | 4 | 4 | 3 | 3 | 1 | — | — | — | — | — |\n| 8-й | +3 | Уничтожение Нечисти (ПО 1), Улучшение | 4 | 4 | 4 | 3 | 3 | 2 | — | — | — | — | — |\n| 9-й | +4 | Божественное Вмешательство | 4 | 5 | 4 | 3 | 3 | 3 | 1 | — | — | — | — |\n| 10-й | +4 | Героический Дар | 5 | 5 | 4 | 3 | 3 | 3 | 2 | — | — | — | — |\n| 11-й | +4 | Уничтожение Нечисти (ПО 2), Умение Подкласса | 5 | 6 | 4 | 3 | 3 | 3 | 2 | 1 | — | — | — |\n| 12-й | +4 | Улучшение | 5 | 6 | 4 | 3 | 3 | 3 | 2 | 1 | — | — | — |\n| 13-й | +5 | Божественный Канал (3/Отдых) | 5 | 7 | 4 | 3 | 3 | 3 | 2 | 1 | 1 | — | — |\n| 14-й | +5 | Уничтожение Нечисти (ПО 3) | 5 | 7 | 4 | 3 | 3 | 3 | 2 | 1 | 1 | — | — |\n| 15-й | +5 | Умение Подкласса | 5 | 8 | 4 | 3 | 3 | 3 | 2 | 1 | 1 | 1 | — |\n| 16-й | +5 | Улучшение | 5 | 8 | 4 | 3 | 3 | 3 | 2 | 1 | 1 | 1 | — |\n| 17-й | +6 | Уничтожение Нечисти (ПО 4) | 5 | 9 | 4 | 3 | 3 | 3 | 2 | 1 | 1 | 1 | 1 |\n| 18-й | +6 | Божественный Канал (4/Отдых) | 5 | 9 | 4 | 3 | 3 | 3 | 3 | 1 | 1 | 1 | 1 |\n| 19-й | +6 | Улучшение | 5 | 9 | 4 | 3 | 3 | 3 | 3 | 2 | 1 | 1 | 1 |\n| 20-й | +6 | Эпический Дар | 5 | 9 | 4 | 3 | 3 | 3 | 3 | 2 | 2 | 1 | 1 |\n\n#### ИСПОЛЬЗОВАНИЕ ЗАКЛИНАНИЙ\n\n**Умение жреца 1-го уровня**\n\nКак проводник божественной силы, вы можете использовать Божественные заклинания.\n\n##### Заговоры\n\nНа 1-м уровне выберите три заговора из списка Божественных заклинаний, чтобы выучить их. Вы выбираете больше Божественных заговоров для изучения на более высоких уровнях, как показано в столбце \"Известные заговоры\" в таблице прогрессии жреца.\n\n##### Подготовка заклинаний\n\nВы должны подготовить заклинания заранее, прежде чем сможете их использовать. Вы можете подготовить любое заклинание из списка Божественных заклинаний из кругов, для которых у вас есть ячейки Божественных заклинаний. (Вы определяете, к каким ячейкам заклинаний у вас есть доступ, проверив свой уровень в таблице прогрессии жреца). Вы можете выбрать количество заклинаний, равное вашему модификатору МДР + ваш уровень жреца (минимум одно заклинание). Это ваш список подготовленных заклинаний, из которых вы можете использовать заклинания.\n\nПодготовка нового списка заклинаний требует времени, проведенного в молитве и медитации: не менее 1 минуты на круг заклинаний для каждого заклинания, которое вы меняете. Вы можете изменить свой список подготовленных заклинаний как часть продолжительного отдыха.\n\n##### Использование заклинаний\n\nВы подготовили количество заклинаний и можете использовать любое из них, используя ячейку Божественного заклинания круга заклинания или выше.\n\nТаблица прогрессии жреца показывает, сколько у вас ячеек Божественных заклинаний на данном уровне. Например, на 3-м уровне у вас есть четыре ячейки 1-го круга и две ячейки 2-го круга, и при 16 МДР вы можете иметь шесть подготовленных заклинаний 1-го или 2-го круга в любой комбинации. Однако у вас есть только две ячейки заклинаний для заклинаний 2-го круга, поэтому, если вы подготовите только заклинания 2-го круга, вы не сможете использовать свои ячейки заклинаний 1-го круга вообще.\n\nИспользование заклинания не удаляет его из вашего списка подготовленных заклинаний, оно просто использует ячейку заклинания. Вы восстанавливаете все использованные ячейки заклинаний, когда заканчиваете продолжительный отдых.\n\n##### Способность к использованию заклинаний\n\nМудрость (МДР) - ваша способность к использованию заклинаний. Ваш модификатор МДР определяет СЛ спасения и модификатор атаки для определенных заклинаний, которые вы используете:\n\n*СЛ спасения от заклинания = 8 + ваш бонус мастерства (БМ) + ваш модификатор МДР*\n\n*Модификатор атаки заклинанием = ваш бонус мастерства (БМ) + ваш модификатор МДР*\n\n##### Ритуалы\n\nВы также можете использовать тип долгосрочного заклинания, называемого ритуалом. Ритуалы не нужно готовить, и они не расходуют ячейки заклинаний.\n\nНа 1-м уровне выберите один ритуал из списка Божественных ритуалов. Вы изучаете больше ритуалов на более высоких уровнях, как показано в столбце \"Известные ритуалы\" таблицы прогрессии жреца, но только из круга, для которого у вас есть ячейки заклинаний. Ритуалы, которые вы изучаете, не учитываются в количестве заклинаний, которые вы изучаете на каждом уровне.\n\n##### Фокус для использования заклинаний\n\nВы можете использовать священный символ в качестве фокуса для использования заклинаний для ваших Божественных заклинаний.\n\n#### ПРОЯВЛЕНИЕ ВЕРЫ\n\n**Умение жреца 1-го уровня**\n\nЖрецы демонстрируют свою веру одним из двух основных способов, владея ею как святой воин или вызывая её как чудотворец. Выберите, как вы проявляете свою веру, с одним из следующих способов.\n\n##### Проявление силы.\n\nВы получаете владение тяжёлой бронёй и одним типом воинского оружия по вашему выбору. Кроме того, вы получаете способность наполнять свои удары оружием божественной энергией: один раз за ход, когда вы попадаете в существо атакой оружием, вы можете нанести дополнительный лучистый или некротический урон (по вашему выбору), равный вашему БМ.\n\n##### Проявление чудес.\n\nВы изучаете один дополнительный заговор по вашему выбору из любого источника магии. Этот заговор считается для вас Божественным, но он не учитывается в количестве известных вам заговоров. Кроме того, вы можете добавить свой БМ к урону, который вы наносите любым Божественным заговором.\n\n#### НАПРАВЛЕНИЕ БОЖЕСТВЕННОЙ СИЛЫ\n\n**Умение жреца 2-го, 6-го, 13-го и 18-го уровней*\n\nВы получаете способность направлять божественную энергию непосредственно от своего божества, чтобы создавать эффекты, выходящие за рамки заклинаний. Вы начинаете с одного эффекта: Изгнание нечестивых. Некоторые подклассы предоставляют дополнительные эффекты по мере продвижения по уровням, как указано в их описаниях.\n\nКогда вы используете свою особенность \"Направление божественной силы\", выберите, какой конкретный эффект вам нужен, например, \"Изгнание нечестивых\". Некоторые из этих эффектов требуют спасения, и в этих случаях СЛ равна СЛ спасения от заклинания жреца.\n\nНачиная со 2-го уровня, вы можете использовать свою особенность \"Направление божественной силы\" один раз до завершения короткого или продолжительного отдыха, затем дважды между отдыхом на 6-м уровне, три раза на 13-м уровне и четыре раза на 18-м уровне. Когда вы заканчиваете короткий или продолжительный отдых, вы восстанавливаете все израсходованные использования.\n\n##### Направление божественной силы: Изгнание нечестивых\n\nВ качестве действия вы представляете свой священный символ и произносите молитву для порицания нечестивых существ. Каждый Дьявол и Нежить по вашему выбору в пределах 30 футов от вас, которые могут видеть или слышать вас, должны совершить спасбросок МДР. Если существо проваливает свой спасение, оно становится изгнанным на 1 минуту или до тех пор, пока не получит какой-либо урон.\n\nИзгнанное существо должно пытаться отодвинуться как можно дальше от вас, хотя оно не может сначала приблизиться к вам, чтобы сделать это. В свой ход оно может использовать только действие \"Рывок\" или иным образом пытаться вырваться из эффекта, который мешает ему двигаться. Если некуда двигаться, оно может использовать действие \"Уклонение\". Оно не может использовать какие-либо реакции.\n\n#### УМЕНИЯ ПОДКЛАССА ЖРЕЦА\n\n**Умение жреца 3-го, 7-го, 11-го и 15-го уровней*\n\nВыберите подкласс, который отражает ваши отношения со своим божеством, Жизнь, Свет или Война (подробно описаны в конце этого класса). Ваш выбор предоставляет вам заклинания и другие особенности на 3-м, 7-м, 11-м и 15-м уровнях.\n\n##### Доменные заклинания\n\nУ каждого подкласса жреца есть список доменных заклинаний, к которым вы можете получить доступ, как только вы сможете использовать заклинания этого круга (как показано в таблице прогрессии жреца). Как только вы получаете такое заклинание, оно всегда у вас подготовлено, и оно не учитывается в количестве заклинаний, которые вы можете подготовить. Однако использование доменного заклинания по-прежнему расходует ячейку Божественного заклинания как обычно.\n\nЕсли одно из этих заклинаний отсутствует в списке Божественных заклинаний, оно по-прежнему считается для вас Божественным заклинанием.\n\n#### УЛУЧШЕНИЕ\n\n**Умение жреца 4-го, 8-го, 12-го, 16-го и 19-го уровней*\n\nВыберите одно из следующих улучшений (значения характеристик не могут быть повышены выше 20 с помощью этой особенности):\n\n* Увеличьте одну характеристику на 2.\n* Увеличьте две разные характеристики на 1 каждую.\n* Увеличьте одну характеристику на 1 и выберите талант из списка магических талантов.\n\n#### УНИЧТОЖЕНИЕ НЕЧЕСТИВЫХ\n\n**Умение жреца 5-го, 8-го, 11-го, 14-го и 17-го уровней*\n\nКогда Дьявол или Нежить проваливают свой спасение против вашей особенности \"Изгнание нечестивых\", они немедленно уничтожаются, если их рейтинг опасности (РО) находится на или ниже определенного порога, как показано в таблице \"Уничтожение нечестивых\".\n\n##### УНИЧТОЖЕНИЕ НЕЧЕСТИВЫХ\n\n| УРОВЕНЬ ЖРЕЦА | УНИЧТОЖАЕТ ДЬЯВОЛОВ ИЛИ НЕЖИТЬ РО... |\n|---|---|\n| 5-й | 1/2 или ниже |\n| 8-й | 1 или ниже |\n| 11-й | 2 или ниже |\n| 14-й | 3 или ниже |\n| 17-й | 4 или ниже |\n\n#### БОЖЕСТВЕННОЕ ВМЕШАТЕЛЬСТВО\n\n**Умение жреца 9-го уровня**\n\nВы можете призвать своё божество вмешаться от вашего имени, когда ваша потребность велика. В начале своего хода вы можете запросить помощь у своего божества, бросив d20 и добавив свой БМ. Если результат равен 19 или ниже, ваш запрос терпит неудачу, и ваше божество не вмешивается. Если результат равен 20 или выше, ваше божество вмешивается от вашего имени, наделяя вас частью своей силы.\n\nЕсли ваше божество вмешивается, вы можете немедленно использовать своё действие, чтобы использовать любое заклинание со временем использования 1 действие из списка Божественных заклинаний или из списка доменных заклинаний, независимо от правил подготовки. Использование заклинания таким образом не расходует ячейку заклинания и не требует материальных компонентов. Если заклинание имеет круг выше, чем вы обычно можете использовать, вы должны совершить проверку характеристики, используя свою способность к использованию заклинаний, чтобы определить, успешно ли вы его используете. СЛ для этой проверки равна 10 + круг заклинания. При неудачной проверке заклинание терпит неудачу, сила вашего божества исчезает, и ваше действие теряется.\n\nВ качестве альтернативы, при успешном вмешательстве ваш ГМ может предложить форму вмешательства. Всё, что воспроизводит эффекты Божественного заклинания, уместно. В этом случае вы по-прежнему используете своё действие, но не используете заклинание. У вас есть последнее слово в разрешении ГМу использовать этот вариант или выборе собственного заклинания.\n\nЕсли ваше божество вмешивается, вы не можете использовать эту особенность снова в течение 1 недели. В противном случае вы можете использовать её снова после завершения продолжительного отдыха.\n\n#### ГЕРОИЧЕСКОЕ БЛАГОСЛОВЕНИЕ\n\n**Умение жреца 10-го уровня**\n\nВаша приверженность пути жреца дарует вам мощную новую способность. Выберите одно из следующих героических благословений:\n\n* **Дар освящения.** Теперь вы невосприимчивы к болезням, урону от яда и отравленному состоянию. Если вы умрёте, ваше тело мгновенно сохраняется в соответствии с заклинанием \"бережное упокоение\" на срок до года и дня.\n* **Дар гнева.** Выберите тип урона: лучистый или некротический. Теперь у вас есть сопротивление урону выбранного типа. Кроме того, когда вы используете заклинание, которое наносит урон любого типа, вы можете выбрать, чтобы оно наносило лучистый или некротический урон (вы выбираете, какой при каждом использовании).\n\n#### ЭПИЧЕСКОЕ БЛАГОСЛОВЕНИЕ\n\n**Умение жреца 20-го уровня**\n\nВаша приверженность пути жреца дарует вам мощную новую способность. Вы получаете следующее эпическое благословение:\n\n* **Божественный вестник.** Когда вы используете свою особенность \"Божественное вмешательство\", ваше божество автоматически вмешивается без броска, и вам больше не нужно ждать неделю, прежде чем вы снова сможете использовать \"Божественное вмешательство\", хотя вы по-прежнему можете использовать его только один раз за продолжительный отдых. Вы по-прежнему связаны другими ограничениями особенности.\n\n### ПОДКЛАСС: ДОМЕН ЖИЗНИ\n\nБоги домена Жизни восхваляют естественные циклы жизни и смерти, демонстрируя здоровье и жизненную силу. Сторонникам этого домена рекомендуется исцелять раненых, заботиться о больных и противостоять извращению нежити.\n\n#### ПРОГРЕССИЯ ДОМЕНА ЖИЗНИ\n\n| УРОВЕНЬ ЖРЕЦА | УМЕНИЯ |\n|---|---|\n| 3-й | Направление божественной силы: Сохранение жизни, Ученик жизни, Заклинания домена Жизни |\n| 7-й | Благословенный целитель |\n| 11-й | Великое сохранение |\n| 15-й | Совершенное исцеление |\n\n#### НАПРАВЛЕНИЕ БОЖЕСТВЕННОЙ СИЛЫ\n\n**Умение Жизни 3-го уровня**\n\nВы получаете следующий вариант \"Направления божественной силы\".\n\n##### Направление божественной силы: Сохранение жизни\n\nВ качестве действия вы представляете свой священный символ и вызываете исцеляющую энергию, которая может восстановить количество хитов, равное 5 × ваш уровень жреца.\n\nВыберите любых существ в пределах 30 футов от вас и разделите эти хиты между ними. Эта особенность может восстановить существу не более половины его максимального количества хитов. Это исцеление не оказывает никакого эффекта на Нежить или Конструктов.\n\n#### УЧЕНИК ЖИЗНИ\n\n**Умение Жизни 3-го уровня**\n\nВаши исцеляющие заклинания более эффективны. Когда вы используете Божественное заклинание 1-го круга или выше, чтобы восстановить хиты существу, существо восстанавливает дополнительные хиты, равные 2 + кругу заклинания.\n\n#### ЗАКЛИНАНИЯ ДОМЕНА ЖИЗНИ\n\n**Умение Жизни 3-го уровня**\n\nВы получаете доменные заклинания на уровнях жреца, указанных в таблице \"Заклинания домена Жизни\". См. особенность класса \"Подкласс жреца\", чтобы узнать, как работают эти заклинания.\n\n##### ЗАКЛИНАНИЯ ДОМЕНА ЖИЗНИ\n\n| УРОВЕНЬ ЖРЕЦА | ЗАКЛИНАНИЯ |\n|---|---|\n| 3-й | благословение, лечение ран, бережное упокоение, восстановление |\n| 5-й | массовое исцеляющее слово, оживление |\n| 7-й | защита от смерти, хранитель веры |\n| 9-й | великое восстановление, массовое лечение ран |\n\n#### БЛАГОСЛОВЕННЫЙ ЦЕЛИТЕЛЬ\n\n**Умение Жизни 7-го уровня**\n\nИсцеляющие заклинания, которые вы используете на других, также исцеляют вас. Когда вы используете Божественное заклинание 1-го круга или выше, которое восстанавливает хиты существу, отличному от вас, вы восстанавливаете хиты, равные 2 + кругу заклинания.\n\n#### ВЕЛИКОЕ СОХРАНЕНИЕ\n\n**Умение Жизни 11-го уровня**\n\nТеперь эффект \"Сохранение жизни\" вашей особенности \"Направление божественной силы\" может влиять на любых существ в пределах 60 футов от вас. Кроме того, когда вы используете \"Сохранение жизни\", одна выбранная вами цель также может получить одно из следующих преимуществ:\n\n* Излечите все болезни, поразившие цель.\n* Прекратите одно из следующих состояний, поразивших цель: ослеплённый, оглушённый, парализованный или отравленный.\n* Нейтрализуйте все яды, поразившие цель.\n\n#### СОВЕРШЕННОЕ ИСЦЕЛЕНИЕ\n\n**Умение Жизни 15-го уровня**\n\nКогда вы используете Божественное заклинание 1-го круга или выше, которое восстанавливает хиты, вы автоматически восстанавливаете максимально возможное количество хитов. Например, если заклинание \"лечение ран\" исцеляет 1d8 + 3 хита, вместо броска цель исцеляет 11 хитов.\n\n### ПОДКЛАСС: ДОМЕН ВОЙНЫ\n\nБоги домена Войны восхваляют силу, славу победы и азарт состязания. Те боги со злыми или хаотичными наклонностями подчеркивают разрушение и насилие, но большинство обществ и героических персонажей поклоняются богам войны, которые чтят храбрость и превосходство в битве и дорожат теми, кто сражается, когда потребность велика.\n\n#### ПРОГРЕССИЯ ДОМЕНА ВОЙНЫ\n\n| УРОВЕНЬ ЖРЕЦА | УМЕНИЯ |\n|---|---|\n| 3-й | Направление божественной силы: Знак триумфа, Ученик войны, Расширенный список талантов, Заклинания домена Войны |\n| 7-й | Благословенный воин |\n| 11-й | Великий триумф |\n| 15-й | Святой удар |\n\n#### НАПРАВЛЕНИЕ БОЖЕСТВЕННОЙ СИЛЫ\n\n**Умение Войны 3-го уровня**\n\nВы получаете следующий вариант \"Направления божественной силы\".\n\n##### Направление божественной силы: Знак триумфа\n\nВ качестве бонусного действия вы представляете свой священный символ и мистически помечаете одно существо в пределах 60 футов от вас, которое вы можете видеть. До начала вашего следующего хода все существа, которые атакуют помеченное существо, имеют преимущество при первом броске атаки, которую они совершают против него.\n\n#### УЧЕНИК ВОЙНЫ\n\n**Умение Войны 3-го уровня**\n\nПобеда приближает вас к божественному, вдохновляя вас выходить за пределы ваших обычных ограничений. Один раз за ход, когда вы успешно попадаете в существо атакой при использовании действия \"Атака\", вы можете совершить дополнительную атаку оружием как часть того же действия.\n\nВы можете использовать эту особенность количество раз, равное вашему БМ. Вы восстанавливаете все израсходованные использования, когда заканчиваете короткий или продолжительный отдых.\n\n#### РАСШИРЕННЫЙ СПИСОК ТАЛАНТОВ\n\n**Умение Войны 3-го уровня**\n\nКогда вы получаете новый талант, вы можете выбрать этот талант из списка магических или воинских талантов.\n\n#### ЗАКЛИНАНИЯ ДОМЕНА ВОЙНЫ\n\n**Умение Войны 3-го уровня**\n\nВы получаете доменные заклинания на уровнях жреца, указанных в таблице \"Заклинания домена Войны\". См. особенность класса \"Подкласс жреца\", чтобы узнать, как работают эти заклинания.\n\n##### ЗАКЛИНАНИЯ ДОМЕНА ВОЙНЫ\n\n| УРОВЕНЬ ЖРЕЦА | ЗАКЛИНАНИЯ |\n|---|---|\n| 3-й | приказ, магическое оружие, щит веры, связывающий оберег |\n| 5-й | страх, духи-хранители |\n| 7-й | защита от смерти, хранитель веры |\n| 9-й | антимагическая оболочка, огненный удар |\n\n#### БЛАГОСЛОВЕННЫЙ ВОИН\n\n**Умение Войны 7-го уровня**\n\nВаши атаки особенно мощны. Когда вы наносите урон оружием или заклинанием, используемым с Божественным заклинанием, вы можете перебросить любой 1, который вы бросите на костях урона. Вы должны взять новый результат для любых костей, переброшенных таким образом.\n\n#### ВЕЛИКИЙ ТРИУМФ\n\n**Умение Войны 11-го уровня**\n\nКогда вы используете эффект \"Знак триумфа\" своей особенности \"Направление божественной силы\", вы можете мистически пометить количество существ, равное вашему БМ. Все цели должны находиться в пределах 60 футов от вас.\n\nКроме того, когда существо, помеченное вашей особенностью \"Знак триумфа\", доведено до 0 ХП, вы можете использовать свою реакцию, чтобы переместить метку на другую цель в пределах 60 футов от вас, которую вы можете видеть. Метка, перемещенная таким образом, по-прежнему исчезает в начале вашего следующего хода, как обычно.\n\n#### СВЯТОЙ УДАР\n\n**Умение Войны 15-го уровня**\n\nОдин раз за ход, когда вы успешно попадаете в существо оружием или заклинанием, используемым с Божественным заклинанием, вы можете рассматривать атаку так, как если бы вы нанесли критический удар.",
  "hitDie": "d8",
  "savingThrows": [
    "МДР",
    "ХАР"
  ],
  "proficiencies": {
    "skills": {
      "granted": [],
      "choose": 2,
      "from": [
        "История",
        "Проницательность",
        "Медицина",
        "Убеждение",
        "Религия"
      ]
    },
    "armor": [
      "Лёгкие доспехи",
      "средние доспехи",
      "щиты"
    ],
    "weapons": [
      "Простое оружие"
    ],
    "tools": [
      "Нет"
    ]
  },
  "startingEquipment": {
    "items": [
      "(a) булава или (b) боевой молот (если владеете).",
      "(a) чешуйчатый доспех, (b) кожаный доспех или (c) кольчуга (если владеете).",
      "(a) лёгкий арбалет и 20 болтов или (b) любое простое оружие.",
      "(a) набор священника или (b) набор исследователя.",
      "Щит и священный символ."
    ]
  },
  "levels": [
    {
      "level": 1,
      "proficiencyBonus": "+2",
      "features": [
        "Проявление Веры",
        "Использование Заклинаний"
      ]
    },
    {
      "level": 2,
      "proficiencyBonus": "+2",
      "features": [
        "Божественный Канал: Изгнание Нечисти (1/Отдых)"
      ]
    },
    {
      "level": 3,
      "proficiencyBonus": "+2",
      "features": [
        "Подкласс Жреца"
      ]
    },
    {
      "level": 4,
      "proficiencyBonus": "+2",
      "features": [
        "Улучшение"
      ]
    },
    {
      "level": 5,
      "proficiencyBonus": "+3",
      "features": [
        "Уничтожение Нечисти (ПО 1/2)"
      ]
    },
    {
      "level": 6,
      "proficiencyBonus": "+3",
      "features": [
        "Божественный Канал (2/Отдых)"
      ]
    },
    {
      "level": 7,
      "proficiencyBonus": "+3",
      "features": [
        "Умение Подкласса"
      ]
    },
    {
      "level": 8,
      "proficiencyBonus": "+3",
      "features": [
        "Уничтожение Нечисти (ПО 1)",
        "Улучшение"
      ]
    },
    {
      "level": 9,
      "proficiencyBonus": "+4",
      "features": [
        "Божественное Вмешательство"
      ]
    },
    {
      "level": 10,
      "proficiencyBonus": "+4",
      "features": [
        "Героический Дар"
      ]
    },
    {
      "level": 11,
      "proficiencyBonus": "+4",
      "features": [
        "Уничтожение Нечисти (ПО 2)",
        "Умение Подкласса"
      ]
    },
    {
      "level": 12,
      "proficiencyBonus": "+4",
      "features": [
        "Улучшение"
      ]
    },
    {
      "level": 13,
      "proficiencyBonus": "+5",
      "features": [
        "Божественный Канал (3/Отдых)"
      ]
    },
    {
      "level": 14,
      "proficiencyBonus": "+5",
      "features": [
        "Уничтожение Нечисти (ПО 3)"
      ]
    },
    {
      "level": 15,
      "proficiencyBonus": "+5",
      "features": [
        "Умение Подкласса"
      ]
    },
    {
      "level": 16,
      "proficiencyBonus": "+5",
      "features": [
        "Улучшение"
      ]
    },
    {
      "level": 17,
      "proficiencyBonus": "+6",
      "features": [
        "Уничтожение Нечисти (ПО 4)"
      ]
    },
    {
      "level": 18,
      "proficiencyBonus": "+6",
      "features": [
        "Божественный Канал (4/Отдых)"
      ]
    },
    {
      "level": 19,
      "proficiencyBonus": "+6",
      "features": [
        "Улучшение"
      ]
    },
    {
      "level": 20,
      "proficiencyBonus": "+6",
      "features": [
        "Эпический Дар"
      ]
    }
  ],
  "features": [],
  "subclasses": [],
  "type": "class",
  "id": "BFRD:class/zhrec",
  "slug": "zhrec",
  "name": "ЖРЕЦ",
  "schemaVersion": "1.0.0",
  "src": {
    "abbr": "BFRD",
    "name": "Black Flag Reference Document",
    "version": "1.0",
    "url": "https://bfrd.net/",
    "license": "Open RPG Creative License (ORC)",
    "hash": "023d60c5d775fa258622e067875d47e55d088ba13dc4050ad6947f5849f1cfdb"
  },
  "summary": "Как жрец, вы обладаете следующими особенностями класса.",
  "sourceFile": "input/classes/cleric.md"
}